Workbook

Sheet Guide
B1: UK SME BANK — BOTTOM-UP UNIT ECONOMICS MODEL
B2: MODEL VERSION: v1.7 · 22 August 2026 — check github.com/tmth-studio/sme-bank-models for the latest; the version history below tells you what changed since your download.
B4: Version history
B5: • v1.7 (22 Aug 2026) — operational leverage. Every cost line in the model scaled linearly with its driver, which forces a cost elasticity of exactly 1.0 and makes cost per customer flat at every scale. Allica Bank's own accounts put that elasticity at 0.808 across 2022-23 and 0.622 across 2023-24 — cost rises materially more slowly than the book. Inputs section O adds a cost scale elasticity and the customer count the per-customer rates are calibrated at; the head-office pools, the platform line and change-the-bank now scale by it. Default 1.0 reproduces v1.6 exactly. Tab 11 adds the out-of-sample test that measured it.
B6: • v1.6 (22 Aug 2026) — validation and drivers. Tab 10 ELASTICITIES: every input bumped +1% and the workbook recalculated, giving the % change in PBT, cost:income, RoE and income. Only one input has an elasticity above 1 on profit — the term loan customer rate, at +1.25; reachable market and penetration are exactly +1.00 (pure scale); nothing else exceeds 0.53. Tab 11 BACKTEST against Allica Bank FY2023 audited accounts: the revenue engine reproduces a real bank's operating income to within 8%, and the cost engine under-predicts by 7x. Diagnosis: head-office cost was modelled purely per customer, which is a scale assumption disguised as a driver. Inputs section N therefore adds a fixed component to each head-office pool, defaulting to 0 so v1.5 results are unchanged.
B7: • v1.5 (22 Aug 2026) — PROCESS LAYER on the Step 2 tabs. Tab 3 gains process columns M-T (process type, yield, attempts, automation, best-in-class intensity and yield, benchmark source, £ gap) and a HEAD-OFFICE PROCESS REGISTER of 22 processes already named in the tab 9 operational model but never costed. Yield inflates ATTEMPTS and never deflates outcomes — that is what stops it double-counting with the CEP layer's demand-side conversion. Head-office costs are carved OUT of the pools, so naming a process moves money from unallocated to attributed and the total never changes. New sheet 3b indexes every process to the numbers it moves, and imputes what each would have to become to hit a target cost:income. Mode OFF (default) = results identical to v1.4.
B8: • v1.4 (22 Aug 2026) — CEP DEMAND LAYER. New sheet 1b derives the nine product penetrations and the customer count instead of asserting them: penetration = (lambda*c x L) / (1 + lambda*c x L), where lambda*c = category-entry-point events x presence x conversion and L is the holding life. Little's Law run forwards; no time axis is added and the model stays a steady-state snapshot. Ships deliberately EMPTY — every event/presence/conversion cell is blank and carries the cohort query that fills it, and any unpopulated product falls back to its hardcoded penetration. Mode OFF (default) = results identical to v1.3; CALIBRATE reports the won-event rate implied by today's assumptions and changes nothing.
B9: • v1.3 (21 Aug 2026) — churn replacement is a costed activity end-to-end: new input cac_new (£240 acquisition marketing per new customer won, carved out of the corporate-centre pool — hq_oh £250→£222); driver-linked on tab 4, attributed to the current account (gateway product) on tab 6; 'value of preventing one churn' memo added to tab 6. Raising the churn input now inflates demand-generation cost, not just processing. Central PBT shifts <£1k/unit (carve-out rounding).
B10: • v1.2.1 (21 Aug 2026) — documentation only: added 'What period this models' to this Guide (steady-state annual snapshot, stationary book, churn replacement costed, transitions out of scope). No formula or input changes — results identical to v1.2.
B11: • v1.2 (12 Aug 2026) — ranges, not points: every input carries Pessimistic/Central/Optimistic (direction-aware) with one scenario toggle driving the ACTIVE column; bands seeded only where benchmark evidence exists (BoE loan rates, Jefferies CoE, peer CET1, BoE SME PD, best-buy savings). Central results identical to v1.1.
B12: • v1.1 (12 Aug 2026) — scenario-building granularity: Channel tag (digital-amenable/judgement) on every activity row (tab 3); per-product RM-held share inputs + RM/digital unit split columns (tab 1). Economics unchanged — tie-out and all product margins identical to v1.0.
B13: • v1.0 (10 Aug 2026) — first published version: 9 tabs + flow register, FTP with liquidity/behavioural terms, fraud/FSCS/change-the-bank lines, segment-pod LMUs, bridge check.
... B48: • The FTP now carries an explicit liquidity charge (buffer × drag) and a behavioural credit for stable deposits, shown as memos on the Revenues tab; it is still a single curve, not a full behavioural-maturity model. Fraud & payment losses, the FSCS levy, collateral administration & recoveries, and change-the-bank spend are now modelled explicitly. Operational-risk RWA is proxied at 15% of gross income; head-office and change costs are allocated per customer.

Sheet Inputs
B1: INPUTS & ASSUMPTIONS — UK SME BANK BOTTOM-UP MODEL
B2: Edit blue cells. Yellow = highest-impact levers. RANGES: every input carries Pessimistic (D) / Central (C) / Optimistic (E) — direction-aware, not numeric low/high; the model runs on ACTIVE (F) via the scenario toggle. Bands are seeded only where benchmark evidence exists; when adapting with your own data, record your uncertainty in D/E rather than flattening to a point.
B4: SCENARIO TOGGLE (1 = pessimistic · 2 = central · 3 = optimistic) | C4: 2
B6: A. MARKET & FUNDING RATES
B7: Item | C7: Central | D7: Pessimistic | E7: Optimistic | F7: ACTIVE | G7: Unit | H7: Source / note
B8: Bank of England Bank Rate | C8: 0.0375 | D8: 0.0375 | E8: 0.0375 | F8: =CHOOSE('Inputs'!$C$4,D8,C8,E8) | G8: % p.a. | H8: BoE Bank Rate held at 3.75%, July 2026 (bankofengland.co.uk; moneysavingexpert.com)
B9: Term funding premium over Bank Rate | C9: 0.006 | D9: 0.006 | E9: 0.006 | F9: =CHOOSE('Inputs'!$C$4,D9,C9,E9) | G9: % p.a. | H9: Assumption: cost of term funding above base — 1yr fixed business deposits pay 4.2–4.6% vs base 3.75% (businessexpert.co.uk, Jul 2026)
B10: Funds transfer price — floating (= Bank Rate) | C10: ='Inputs'!$F$8 | F10: =C10 | G10: % p.a. | H10: Internal transfer price credited to deposits / charged to floating lending
B11: Funds transfer price — term (= Bank Rate + premium) | C11: ='Inputs'!$F$8+'Inputs'!$F$9 | F11: =C11 | G11: % p.a. | H11: Charged to term/fixed-rate lending; credited to term deposits
B12: A2. LIQUIDITY & FUNDING (explicit FTP: liquidity charge + behavioural deposit credit)
B13: Item | C13: Central | D13: Pessimistic | E13: Optimistic | F13: ACTIVE | G13: Unit | H13: Source / note
B14: Liquidity buffer held against deposits (LCR / HQLA) | C14: 0.15 | D14: 0.15 | E14: 0.15 | F14: =CHOOSE('Inputs'!$C$4,D14,C14,E14) | G14: % of deposits | H14: Assumption: high-quality liquid assets held against deposit-outflow risk
B15: Yield give-up on the liquidity buffer vs Bank Rate | C15: 0.01 | D15: 0.01 | E15: 0.01 | F15: =CHOOSE('Inputs'!$C$4,D15,C15,E15) | G15: % p.a. | H15: Assumption: HQLA (gilts, central-bank reserves) yield below Bank Rate — the cost of holding the buffer
B16: Behavioural term credit for stable non-maturing deposits | C16: 0.005 | D16: 0.005 | E16: 0.005 | F16: =CHOOSE('Inputs'!$C$4,D16,C16,E16) | G16: % p.a. | H16: Assumption: sticky current-account and savings balances behave long, so earn a term uplift over the float FTP
B17: FTP credited to stable deposits (float − liquidity charge + behavioural credit) | C17: ='Inputs'!$F$10-'Inputs'!$F$14*'Inputs'!$F$15+'Inputs'!$F$16 | F17: =C17 | G17: % p.a. | H17: Applied to current accounts and instant savings — makes the deposit-funding value explicit
B18: FTP credited to term deposits (term − liquidity charge) | C18: ='Inputs'!$F$11-'Inputs'!$F$14*'Inputs'!$F$15 | F18: =C18 | G18: % p.a. | H18: Applied to notice & fixed deposits (already termed; no behavioural uplift)
B19: B. OPERATING UNIT — REGIONAL BUSINESS CENTRE (Simanis Step 1: bounding)
B20: Item | C20: Central | D20: Pessimistic | E20: Optimistic | F20: ACTIVE | G20: Unit | H20: Source / note
B21: Reachable SMEs in region (R) | C21: 18750 | D21: 18750 | E21: 18750 | F21: =CHOOSE('Inputs'!$C$4,D21,C21,E21) | G21: businesses | H21: Catchment per centre: UK's ~5.6m businesses (DBT Business Population Estimates) ÷ 300 centres of national coverage
B22: Steady-state penetration (P) | C22: 0.16 | D22: 0.16 | E22: 0.16 | F22: =CHOOSE('Inputs'!$C$4,D22,C22,E22) | G22: % of reachable | H22: Set so 300 centres × 3,000 customers = 900,000 BCA customers — a ~16% national SME market share, i.e. big-4 incumbent territory (Barclays/Lloyds each serve ~1m+ business customers)
B23: Annual customer churn (replaced at steady state) | C23: 0.12 | D23: 0.12 | E23: 0.12 | F23: =CHOOSE('Inputs'!$C$4,D23,C23,E23) | G23: % p.a. | H23: Assumption: SME banking attrition; drives onboarding workload
B24: Share of customers that are relationship-managed | C24: 0.15 | D24: 0.15 | E24: 0.15 | F24: =CHOOSE('Inputs'!$C$4,D24,C24,E24) | G24: % | H24: SEGMENT BOUNDARY: larger SMEs (by turnover/complexity) get a named RM; the small-business mass is served digitally
B25: Customers per relationship manager (L) | C25: 120 | D25: 120 | E25: 120 | F25: =CHOOSE('Inputs'!$C$4,D25,C25,E25) | G25: customers | H25: Assumption: RM portfolio size (customer load)
B26: RMs per relationship pod | C26: 6 | D26: 6 | E26: 6 | F26: =CHOOSE('Inputs'!$C$4,D26,C26,E26) | G26: RMs | H26: Segment-bounded LMU: a relationship pod = pod lead + RMs + analysts; capacity = RMs × portfolio
B27: Service & ops FTE per digital service pod | C27: 10 | D27: 10 | E27: 10 | F27: =CHOOSE('Inputs'!$C$4,D27,C27,E27) | G27: FTE | H27: Segment-bounded LMU: a digital pod serves the small-business segment via app + contact centre
B28: C. PRODUCT HOLDINGS & BALANCES (per customer)
B29: Item | C29: Central | D29: Pessimistic | E29: Optimistic | F29: ACTIVE | G29: Unit | H29: Source / note
B30: Business current account — penetration | C30: 1 | D30: 1 | E30: 1 | F30: =CHOOSE('Inputs'!$C$4,D30,C30,E30) | G30: % of customers | H30: Anchor product: every customer holds a BCA
B31: BCA — average credit balance | C31: 18000 | D31: 14000 | E31: 22000 | F31: =CHOOSE('Inputs'!$C$4,D31,C31,E31) | G31: £/account | H31: Assumption — NO public benchmark exists (top internal-validation item); wide band reflects that
B32: Instant-access savings — penetration | C32: 0.4 | D32: 0.4 | E32: 0.4 | F32: =CHOOSE('Inputs'!$C$4,D32,C32,E32) | G32: % | H32: Assumption
B33: Instant-access savings — average balance | C33: 30000 | D33: 30000 | E33: 30000 | F33: =CHOOSE('Inputs'!$C$4,D33,C33,E33) | G33: £/account | H33: Assumption
B34: Notice & fixed deposits — penetration | C34: 0.15 | D34: 0.15 | E34: 0.15 | F34: =CHOOSE('Inputs'!$C$4,D34,C34,E34) | G34: % | H34: Assumption
B35: Notice & fixed deposits — average balance | C35: 75000 | D35: 75000 | E35: 75000 | F35: =CHOOSE('Inputs'!$C$4,D35,C35,E35) | G35: £/account | H35: Assumption
B36: Overdraft — penetration | C36: 0.25 | D36: 0.25 | E36: 0.25 | F36: =CHOOSE('Inputs'!$C$4,D36,C36,E36) | G36: % | H36: Assumption: share of customers with a facility
B37: Overdraft — average limit | C37: 15000 | D37: 15000 | E37: 15000 | F37: =CHOOSE('Inputs'!$C$4,D37,C37,E37) | G37: £/facility | H37: Assumption
B38: Overdraft — average utilisation | C38: 0.45 | D38: 0.45 | E38: 0.45 | F38: =CHOOSE('Inputs'!$C$4,D38,C38,E38) | G38: % of limit | H38: Assumption
B39: Term loans / commercial mortgages — penetration | C39: 0.12 | D39: 0.12 | E39: 0.12 | F39: =CHOOSE('Inputs'!$C$4,D39,C39,E39) | G39: % | H39: Assumption
B40: Term loans — average balance | C40: 250000 | D40: 250000 | E40: 250000 | F40: =CHOOSE('Inputs'!$C$4,D40,C40,E40) | G40: £/loan | H40: Assumption
B41: Term loans — average life | C41: 4 | D41: 4 | E41: 4 | F41: =CHOOSE('Inputs'!$C$4,D41,C41,E41) | G41: years | H41: Assumption: drives origination volume & fee amortisation
... B55: International payments — number per user per year | C55: 30 | D55: 30 | E55: 30 | F55: =CHOOSE('Inputs'!$C$4,D55,C55,E55) | G55: payments | H55: Assumption
B56: D. PRICING & FEES
B57: Item | C57: Central | D57: Pessimistic | E57: Optimistic | F57: ACTIVE | G57: Unit | H57: Source / note
B58: BCA — credit interest paid | C58: 0.005 | D58: 0.005 | E58: 0.005 | F58: =CHOOSE('Inputs'!$C$4,D58,C58,E58) | G58: % p.a. | H58: Assumption: most BCAs pay 0–1%
B59: BCA — monthly account fee | C59: 8.5 | D59: 8.5 | E59: 8.5 | F59: =CHOOSE('Inputs'!$C$4,D59,C59,E59) | G59: £/month | H59: Barclays standard business tariff from £8.50/mo post free period; NatWest £5–10 (anna.money comparison, 2026)
B60: BCA — net transaction & cash-handling income | C60: 120 | D60: 120 | E60: 120 | F60: =CHOOSE('Inputs'!$C$4,D60,C60,E60) | G60: £/account/yr | H60: Assumption: net of payment costs; cash deposits charged 0.5–0.7% of value at majors (anna.money)
B61: Instant-access savings — rate paid | C61: 0.033 | D61: 0.0386 | E61: 0.032 | F61: =CHOOSE('Inputs'!$C$4,D61,C61,E61) | G61: % p.a. | H61: Best-buy 3.86–3.91% Jul 2026; established banks price below — pessimistic = pushed to best-buy
B62: Notice & fixed deposits — rate paid | C62: 0.041 | D62: 0.041 | E62: 0.041 | F62: =CHOOSE('Inputs'!$C$4,D62,C62,E62) | G62: % p.a. | H62: Notice ~4.0%, 1-yr fixed 4.2–4.6% Jul 2026 (businessexpert.co.uk)
B63: Overdraft — interest rate (EAR) | C63: 0.0975 | D63: 0.0975 | E63: 0.0975 | F63: =CHOOSE('Inputs'!$C$4,D63,C63,E63) | G63: % p.a. | H63: Assumption: typical SME overdraft margins ~5–7% over base (major-bank rep rates)
B64: Overdraft — annual arrangement/renewal fee | C64: 0.015 | D64: 0.015 | E64: 0.015 | F64: =CHOOSE('Inputs'!$C$4,D64,C64,E64) | G64: % of limit | H64: Assumption: 1–2% of limit is typical
B65: Term loans — customer rate | C65: 0.0625 | D65: 0.0611 | E65: 0.064 | F65: =CHOOSE('Inputs'!$C$4,D65,C65,E65) | G65: % p.a. | H65: BoE effective new-SME rate 6.11% Mar 2026 (base+236bps); band seeded from market evidence
B66: Term loans — arrangement fee | C66: 0.015 | D66: 0.015 | E66: 0.015 | F66: =CHOOSE('Inputs'!$C$4,D66,C66,E66) | G66: % of loan | H66: Assumption: 1–2% typical; amortised over loan life in the model
B67: Asset finance — customer yield | C67: 0.085 | D67: 0.085 | E67: 0.085 | F67: =CHOOSE('Inputs'!$C$4,D67,C67,E67) | G67: % p.a. | H67: Assumption: HP/lease yields ~8–9% for SME kit
B68: Invoice finance — discount margin over base | C68: 0.025 | D68: 0.025 | E68: 0.025 | F68: =CHOOSE('Inputs'!$C$4,D68,C68,E68) | G68: % p.a. | H68: Discount charge typically base +1–3% (marketinvoice.co.uk, 2026)
B69: Invoice finance — service fee | C69: 0.01 | D69: 0.01 | E69: 0.01 | F69: =CHOOSE('Inputs'!$C$4,D69,C69,E69) | G69: % of funded invoices | H69: Service charge typically 0.5–3% of invoice value (marketinvoice.co.uk)
... B74: International payment fee | C74: 17.5 | D74: 17.5 | E74: 17.5 | F74: =CHOOSE('Inputs'!$C$4,D74,C74,E74) | G74: £/payment | H74: Major banks charge £15–25 per international payment (anna.money)
B75: E. CREDIT RISK, CAPITAL & TAX (Simanis Step 3: investment costs)
B76: Item | C76: Central | D76: Pessimistic | E76: Optimistic | F76: ACTIVE | G76: Unit | H76: Source / note
B77: Overdraft — probability of default | C77: 0.026 | D77: 0.026 | E77: 0.026 | F77: =CHOOSE('Inputs'!$C$4,D77,C77,E77) | G77: % p.a. | H77: BoE: retail SME PD ~2.6% vs 0.9% mid/large corporates (BoE Bank Insights 2026)
B78: Overdraft — loss given default | C78: 0.55 | D78: 0.55 | E78: 0.55 | F78: =CHOOSE('Inputs'!$C$4,D78,C78,E78) | G78: % | H78: Assumption: unsecured working capital
B79: Term loans — probability of default | C79: 0.018 | D79: 0.026 | E79: 0.015 | F79: =CHOOSE('Inputs'!$C$4,D79,C79,E79) | G79: % p.a. | H79: Assumption: secured book below unsecured SME PD (BoE retail SME 2.6%); band seeded
B80: Term loans — loss given default | C80: 0.25 | D80: 0.25 | E80: 0.25 | F80: =CHOOSE('Inputs'!$C$4,D80,C80,E80) | G80: % | H80: Assumption: property/security-backed
B81: Asset finance — probability of default | C81: 0.022 | D81: 0.022 | E81: 0.022 | F81: =CHOOSE('Inputs'!$C$4,D81,C81,E81) | G81: % p.a. | H81: Assumption
B82: Asset finance — loss given default | C82: 0.35 | D82: 0.35 | E82: 0.35 | F82: =CHOOSE('Inputs'!$C$4,D82,C82,E82) | G82: % | H82: Assumption: recoverable assets
B83: Invoice finance — probability of default | C83: 0.026 | D83: 0.026 | E83: 0.026 | F83: =CHOOSE('Inputs'!$C$4,D83,C83,E83) | G83: % p.a. | H83: Assumption
B84: Invoice finance — loss given default | C84: 0.2 | D84: 0.2 | E84: 0.2 | F84: =CHOOSE('Inputs'!$C$4,D84,C84,E84) | G84: % | H84: Assumption: secured on receivables
B85: Card — probability of default | C85: 0.035 | D85: 0.035 | E85: 0.035 | F85: =CHOOSE('Inputs'!$C$4,D85,C85,E85) | G85: % p.a. | H85: Assumption
B86: Card — loss given default | C86: 0.75 | D86: 0.75 | E86: 0.75 | F86: =CHOOSE('Inputs'!$C$4,D86,C86,E86) | G86: % | H86: Assumption: unsecured
B87: Overdraft — risk weight | C87: 0.75 | D87: 0.75 | E87: 0.75 | F87: =CHOOSE('Inputs'!$C$4,D87,C87,E87) | G87: % of drawn | H87: Standardised retail SME treatment (approx., incl. SME support factor)
B88: Term loans — risk weight | C88: 0.7 | D88: 0.7 | E88: 0.7 | F88: =CHOOSE('Inputs'!$C$4,D88,C88,E88) | G88: % | H88: Approximation incl. SME support factor (BoE notes 15–24% RWA reduction)
... B95: Tax rate (corporation tax + bank surcharge) | C95: 0.28 | D95: 0.28 | E95: 0.28 | F95: =CHOOSE('Inputs'!$C$4,D95,C95,E95) | G95: % | H95: 25% UK corporation tax + 3% bank surcharge on profits above allowance
B96: F. PEOPLE & ACTIVITY DRIVERS (Simanis Step 2: transaction intensity I & customer load L)
B97: Item | C97: Central | D97: Pessimistic | E97: Optimistic | F97: ACTIVE | G97: Unit | H97: Source / note
B98: Productive hours per FTE per month | C98: 147 | D98: 147 | E98: 147 | F98: =CHOOSE('Inputs'!$C$4,D98,C98,E98) | G98: hours | H98: Convention: 147 productive hours per FTE per month
B99: Relationship manager — salary | C99: 65000 | D99: 65000 | E99: 65000 | F99: =CHOOSE('Inputs'!$C$4,D99,C99,E99) | G99: £/yr | H99: Assumption: UK commercial banking RM
B100: Credit analyst / underwriter — salary | C100: 55000 | D100: 55000 | E100: 55000 | F100: =CHOOSE('Inputs'!$C$4,D100,C100,E100) | G100: £/yr | H100: Assumption
B101: Service & operations staff — salary | C101: 32000 | D101: 32000 | E101: 32000 | F101: =CHOOSE('Inputs'!$C$4,D101,C101,E101) | G101: £/yr | H101: Assumption
B102: Team manager — salary | C102: 85000 | D102: 85000 | E102: 85000 | F102: =CHOOSE('Inputs'!$C$4,D102,C102,E102) | G102: £/yr | H102: Assumption
B103: Employment on-costs (NI, pension, benefits) | C103: 0.15 | D103: 0.15 | E103: 0.15 | F103: =CHOOSE('Inputs'!$C$4,D103,C103,E103) | G103: % of salary | H103: Assumption: UK employer on-costs
B104: Management span (staff per manager) | C104: 8 | D104: 8 | E104: 8 | F104: =CHOOSE('Inputs'!$C$4,D104,C104,E104) | G104: staff | H104: Assumption
B105: Onboarding a new customer (KYC/AML + setup) | C105: 2.5 | D105: 2.5 | E105: 2.5 | F105: =CHOOSE('Inputs'!$C$4,D105,C105,E105) | G105: hrs/new customer | H105: Assumption
B106: BCA servicing (queries, payments support) | C106: 0.6 | D106: 0.6 | E106: 0.6 | F106: =CHOOSE('Inputs'!$C$4,D106,C106,E106) | G106: hrs/account/yr | H106: Assumption
B107: Savings account servicing | C107: 0.2 | D107: 0.2 | E107: 0.2 | F107: =CHOOSE('Inputs'!$C$4,D107,C107,E107) | G107: hrs/account/yr | H107: Assumption
B108: Deposit account servicing | C108: 0.2 | D108: 0.2 | E108: 0.2 | F108: =CHOOSE('Inputs'!$C$4,D108,C108,E108) | G108: hrs/account/yr | H108: Assumption
B109: Overdraft annual review & renewal | C109: 1.5 | D109: 1.5 | E109: 1.5 | F109: =CHOOSE('Inputs'!$C$4,D109,C109,E109) | G109: hrs/facility/yr | H109: Assumption
... B122: Recoveries & workout (defaulted secured facilities) | C122: 8 | D122: 8 | E122: 8 | F122: =CHOOSE('Inputs'!$C$4,D122,C122,E122) | G122: hrs/case | H122: Assumption: specialist recoveries beyond routine collections
B123: G. OVERHEADS & HEAD-OFFICE ALLOCATION
B124: Item | C124: Central | D124: Pessimistic | E124: Optimistic | F124: ACTIVE | G124: Unit | H124: Source / note
B125: Premises & facilities per unit FTE | C125: 6000 | D125: 6000 | E125: 6000 | F125: =CHOOSE('Inputs'!$C$4,D125,C125,E125) | G125: £/FTE/yr | H125: Assumption: regional office cost
B126: Equipment & fit-out depreciation per unit FTE | C126: 1200 | D126: 1200 | E126: 1200 | F126: =CHOOSE('Inputs'!$C$4,D126,C126,E126) | G126: £/FTE/yr | H126: Assumption
B127: Other direct running costs (travel, training, sundry) | C127: 0.05 | D127: 0.05 | E127: 0.05 | F127: =CHOOSE('Inputs'!$C$4,D127,C127,E127) | G127: % of unit HR cost | H127: Assumption
B128: Unit-level platform & processing cost | C128: 60 | D128: 60 | E128: 60 | F128: =CHOOSE('Inputs'!$C$4,D128,C128,E128) | G128: £/customer/yr | H128: Assumption: per-account core banking & payment processing
B129: Head office: technology & central operations | C129: 450 | D129: 550 | E129: 380 | F129: =CHOOSE('Inputs'!$C$4,D129,C129,E129) | G129: £/customer/yr | H129: Assumption: allocated share of core banking, digital channels, payments infrastructure; banded
B130: Head office: risk, compliance, financial crime, audit | C130: 250 | D130: 250 | E130: 250 | F130: =CHOOSE('Inputs'!$C$4,D130,C130,E130) | G130: £/customer/yr | H130: Assumption
B131: Head office: finance, HR, exec, brand & residual (non-acquisition) marketing | C131: 222 | D131: 222 | E131: 222 | F131: =CHOOSE('Inputs'!$C$4,D131,C131,E131) | G131: £/customer/yr | H131: Assumption: HQ lines calibrated so cost:income ratio lands ~40–50% (specialist SME banks: OakNorth ~26%, Allica ~50%, majors' business banking 50%+). v1.3: acquisition-directed marketing (~£28/customer/yr central) carved out into cac_new — the churn-replacement activity
B132: G2. DRIVER-BASED ATTRIBUTION OF HEAD-OFFICE POOLS (ABC to the causality limit)
B133: Item | C133: Central | D133: Pessimistic | E133: Optimistic | F133: ACTIVE | G133: Unit | H133: Source / note
B134: KYC & financial crime — cost per new-customer onboarding | C134: 150 | D134: 150 | E134: 150 | F134: =CHOOSE('Inputs'!$C$4,D134,C134,E134) | G134: £/new customer | H134: Driver: onboardings. Attributed from the risk pool; per source methodology, costs are linked to the customer base 'whenever possible' (Simanis IFC Technical Doc, Part II)
B135: KYC refresh & ongoing screening — cost per customer | C135: 60 | D135: 60 | E135: 60 | F135: =CHOOSE('Inputs'!$C$4,D135,C135,E135) | G135: £/customer/yr | H135: Driver: customers. Attributed from the risk pool
B136: Churn replacement — acquisition marketing per new customer won | C136: 240 | D136: 240 | E136: 240 | F136: =CHOOSE('Inputs'!$C$4,D136,C136,E136) | G136: £/new customer | H136: Driver: net churn replacement (tab 1). Demand-generation spend (media, campaigns, incentives) to win the replacement relationship — carved out of the corporate-centre pool so the churn lever inflates the FULL replacement cost, not just processing. Benchmark: SME CAC £150–500/customer; BCR incentive schemes paid far more. RM origination effort (lending) and onboarding processing (KYC, setup hours) are costed separately
B137: Payments operations & processing — cost per current account | C137: 120 | D137: 120 | E137: 120 | F137: =CHOOSE('Inputs'!$C$4,D137,C137,E137) | G137: £/BCA/yr | H137: Driver: current accounts (the transaction-carrying product). Attributed from the tech pool
...

Sheet 1. Customers
B1: STEP 1 — BOUNDING THE OPERATING UNIT
B2: SME banks organise by CUSTOMER SEGMENT, not geography (Simanis: digital offerings bound the LMU by 'a defined customer segment'). The operational LMUs are segment pods — relationship pods and digital service pods (Org tab, 'Segment pods'). This tab models a 1/300 slice of the national book purely for unit economics; the slice is a modelling construct, not the operating unit.
B4: Customers at steady state | C4: ='1b. Demand & CEPs'!$G$21 | E4: CEP layer OFF/CALIBRATE → reachable market × steady-state penetration. LIVE → derived from acquisition CEPs (sheet 1b).
B5: …of which relationship-managed | C5: ='1. Customers'!$C$4*'Inputs'!$F$24
B6: Customers lost per year before RM defence (gross churn) | C6: ='1. Customers'!$C$4*'Inputs'!$F$23
B7: …customers defended by RM retention activity | C7: ='1. Customers'!$C$5*'Inputs'!$F$23*'Inputs'!$F$168 | E7: RM-managed churn × defence effect (validate with holdouts)
B8: New customers onboarded per year (net churn replacement) | C8: ='1. Customers'!$C$6-'1. Customers'!$C$7 | E8: Drives onboarding workload and KYC costs
B10: PRODUCT VOLUMES & BALANCES
B11: Product | C11: Units (accounts / facilities) | D11: Avg balance per unit (£) | E11: Total balances (£) | F11: Note | G11: RM-held units | H11: Digitally-held units | I11: (segment granularity — scenario dimension)
B12: Business current accounts | C12: ='1. Customers'!$C$4*'Inputs'!$F$30 | D12: ='Inputs'!$F$31 | E12: =C12*D12 | F12: Credit balances held by customers | G12: =C12*'Inputs'!$F$148 | H12: =C12-G12
B13: Instant-access savings | C13: ='1. Customers'!$C$4*'1b. Demand & CEPs'!$J$41 | D13: ='Inputs'!$F$33 | E13: =C13*D13 | G13: =C13*'Inputs'!$F$149 | H13: =C13-G13
B14: Notice & fixed deposits | C14: ='1. Customers'!$C$4*'1b. Demand & CEPs'!$J$42 | D14: ='Inputs'!$F$35 | E14: =C14*D14 | G14: =C14*'Inputs'!$F$150 | H14: =C14-G14
B15: Business overdrafts | C15: ='1. Customers'!$C$4*'1b. Demand & CEPs'!$J$43 | D15: ='Inputs'!$F$37*'Inputs'!$F$38 | E15: =C15*D15 | F15: Balance = limit × utilisation (drawn) | G15: =C15*'Inputs'!$F$151 | H15: =C15-G15
B16: Term loans & comm. mortgages | C16: ='1. Customers'!$C$4*'1b. Demand & CEPs'!$J$44 | D16: ='Inputs'!$F$40 | E16: =C16*D16 | G16: =C16*'Inputs'!$F$152 | H16: =C16-G16
B17: Asset finance | C17: ='1. Customers'!$C$4*'1b. Demand & CEPs'!$J$45 | D17: ='Inputs'!$F$43 | E17: =C17*D17 | G17: =C17*'Inputs'!$F$153 | H17: =C17-G17
B18: Invoice finance | C18: ='1. Customers'!$C$4*'1b. Demand & CEPs'!$J$46 | D18: ='Inputs'!$F$46 | E18: =C18*D18 | F18: Funds in use (advances outstanding) | G18: =C18*'Inputs'!$F$154 | H18: =C18-G18
B19: Business credit cards | C19: ='1. Customers'!$C$4*'1b. Demand & CEPs'!$J$47 | D19: ='Inputs'!$F$52*'Inputs'!$F$51 | E19: =C19*D19 | F19: Avg interest-bearing balance per card | G19: =C19*'Inputs'!$F$155 | H19: =C19-G19
B20: Payments & FX (service users) | C20: ='1. Customers'!$C$4*'Inputs'!$F$53 | D20: =0 | E20: =C20*D20 | F20: No balance product | G20: =C20*'Inputs'!$F$156 | H20: =C20-G20
B21: Total customer deposits | E21: ='1. Customers'!$E$12+'1. Customers'!$E$13+'1. Customers'!$E$14
B22: Total lending balances | E22: ='1. Customers'!$E$15+'1. Customers'!$E$16+'1. Customers'!$E$17+'1. Customers'!$E$18+'1. Customers'!$E$19
D23: ='1. Customers'!$E$22/'1. Customers'!$E$21 | E23: Loan-to-deposit ratio:
B24: Total accounts on ledger (all products excl. FX users) | C24: ='1. Customers'!$C$12+'1. Customers'!$C$13+'1. Customers'!$C$14+'1. Customers'!$C$15+'1. Customers'!$C$16+'1. Customers'!$C$17+'1. Customers'!$C$18+'1. Customers'!$C$19 | E24: Driver for core banking system cost
B25: Total live credit facilities | C25: ='1. Customers'!$C$15+'1. Customers'!$C$16+'1. Customers'!$C$17+'1. Customers'!$C$18+'1. Customers'!$C$19 | E25: Driver for credit systems & monitoring cost

Sheet 1b. Demand & CEPs
B1: DEMAND LAYER — CATEGORY ENTRY POINTS
B2: One job to be done: 'I keep the business's money working.' A category entry point is a SITUATION in which that job arises — not a segment, not a product feature. At steady state a stock and a rate are the same statement (Little's Law), so this layer needs no time axis: penetration = (lambda*c x L) / (1 + lambda*c x L), where lambda*c = events x presence x conversion won per customer per year and L is the holding life. The saturating form is used because a customer holds at most one of each product at a time; it is bounded at 1, so no scenario can produce a penetration above 100%.
B3: SHIPPING POSTURE: the event, presence and conversion columns ship EMPTY on purpose. Each carries the cohort query that fills it. Assumed incidence rates get contradicted by a bank's own data inside one meeting, and that discredits the parts of the model that are right. Any product whose rows are unpopulated falls back to its hardcoded penetration, so the workbook is complete and inert until a bank fills it in.
B5: Mode (set on Inputs) | C5: ='Inputs'!$F$190
B7: FAMILY A — ACQUISITION CEPs (derive the customer count)
B8: ID | C8: Category entry point | D8: Events in catchment /yr | E8: Presence | F8: Conversion | G8: Won events /yr | H8: Tier | I8: Cost to be present (£/yr) | J8: Cohort query that fills this row
B9: A1 | C9: The business is formed or starts trading | G9: =IFERROR(D9*E9*F9,0) | H9: T2 | J9: [mental availability] Companies House incorporations in catchment postcodes /yr. Presence = prompted consideration at formation (brand tracker). Evidence held: >50% of start-ups default to the founder's personal-account bank (CMA 2016).
B10: A2 | C10: A service failure, fee shock or declined request breaks trust | G10: =IFERROR(D10*E10*F10,0) | H10: T2 | J10: [detection / rivals' availability] Complaints + fee-shock events + declines on own book /yr; for inbound, CASS switch-ins by stated reason. Evidence held: switching after formation runs 0.5-4%/yr.
B11: A3 | C11: A credit need arises the incumbent will not meet | G11: =IFERROR(D11*E11*F11,0) | H11: T4 | J11: [mental availability + broker] Broker-introduced applications /yr + declined-elsewhere flag on inbound applications.
B12: A4 | C12: Ownership or structure changes (incorporation, sale, merger) | G12: =IFERROR(D12*E12*F12,0) | H12: T4 | J12: [mental availability] Companies House filings for share transfers and re-registrations in catchment /yr.
B13: A5 | C13: An inducement is offered | G13: =IFERROR(D13*E13*F13,0) | H13: T2 | J13: [paid] Switch-offer redemptions /yr. Evidence held: BCR ISS moved 69,135 SMEs, GBP251.54m, >50% of all CASS SME switches in 28 months. Post-dowry retention was never published — loyalty purchase is unproven in both directions.
C14: Won acquisition events /yr | G14: =SUM(G9:G13) | I14: =SUM(I9:I13)
C15: Relationship life (= 1 / churn) | G15: =1/'Inputs'!$F$23
C16: Derived customers (won events x relationship life) | G16: ='1b. Demand & CEPs'!$G$14*'1b. Demand & CEPs'!$G$15
C17: Hardcoded customers (R x P) | G17: ='Inputs'!$F$21*'Inputs'!$F$22
C18: CALIBRATE — won events/yr implied by today's R x P | G18: ='1b. Demand & CEPs'!$G$17/'1b. Demand & CEPs'!$G$15 | J18: This is the number the five CEPs above must sum to. It equals the onboarding volume the model already computes on tab 1, so Little's Law closes on the acquisition side.
C19: MEMO — acquisition cost per won event | G19: =IFERROR('1b. Demand & CEPs'!$I$14/'1b. Demand & CEPs'!$G$14,0) | J19: Memo only in v1.3 — not posted to the P&L, so toggle OFF stays byte-identical. The current account, cards, savings and FX carry no acquisition cost anywhere in the model; this is the first place it is quantified.
C21: Customers in force | G21: =IF('1b. Demand & CEPs'!$C$5<>"LIVE",'1b. Demand & CEPs'!$G$17,IF('1b. Demand & CEPs'!$G$14=0,'1b. Demand & CEPs'!$G$17,'1b. Demand & CEPs'!$G$16))
B23: FAMILY B — CROSS-HOLDING CEPs (derive the eight product penetrations)
C24: The current account has no row here. It is the relationship itself, so it is derived by Family A and its penetration stays 100% by definition.
B25: ID | C25: Category entry point | D25: Events /cust/yr | E25: Presence | F25: Conversion | G25: Won /cust/yr | H25: Tier | I25: Product | J25: Cohort query that fills this row
B26: B1 | C26: A surplus balance sits idle past a threshold | G26: =IFERROR(D26*E26*F26,0) | H26: T1 | I26: sav | J26: [detection + default] Customer-months where the current-account balance exceeds a threshold for 90 days. Evidence held: GBP150bn of SME deposits sit inert; FCA auto-enrolment cut unpaid-item charges 21-24% where the self-registration arm achieved nothing. This is a default, not a campaign.
B27: B2 | C27: A known outgoing is dated 3-12 months ahead | G27: =IFERROR(D27*E27*F27,0) | H27: T4 | I27: dep | J27: [detection] Scheduled large debits (tax, planned capex) visible on the account 3-12 months out.
B28: B3 | C28: A balance approaches zero or a payment nearly fails | G28: =IFERROR(D28*E28*F28,0) | H28: T1 | I28: od | J28: [detection + alert] Near-miss events /customer/yr: balance below buffer, or a payment attempted against insufficient funds. Evidence held: FCA OP36/OP40 alerts cut unarranged charges ~25% — the only T1 evidence in UK banking.
B29: B4 | C29: A capital purchase or premises decision arises | G29: =IFERROR(D29*E29*F29,0) | H29: T4 | I29: loan | J29: [RM (already costed)] Loan applications by stated purpose = expansion or premises, per customer per year.
B30: B5 | C30: An existing facility reaches maturity | G30: =IFERROR(D30*E30*F30,0) | H30: T4 | I30: loan | J30: [RM (already costed)] Facilities reaching maturity /yr, from the book's own maturity ladder.
B31: B6 | C31: Equipment or a vehicle reaches end of life | G31: =IFERROR(D31*E31*F31,0) | H31: T4 | I31: af | J31: [RM (already costed)] Asset finance agreements reaching end of term, plus asset-register age where held.
B32: B7 | C32: A debtor goes past terms and opens a cash gap | G32: =IFERROR(D32*E32*F32,0) | H32: T4 | I32: inv | J32: [RM (already costed)] Customer-months where receivables ageing crosses terms — visible from transaction data on the current account.
B33: B8 | C33: An order arrives too large for working capital | G33: =IFERROR(D33*E33*F33,0) | H33: T4 | I33: inv | J33: [RM (already costed)] Single credits or invoices above a multiple of the customer's mean monthly turnover.
B34: B9 | C34: Recurring supplier spend needs separating from the account | G34: =IFERROR(D34*E34*F34,0) | H34: T2 | I34: card | J34: [default at onboarding] Customers with recurring card-type spend running through the current account. Evidence held: defaults beat persuasion — card-as-default-instrument at onboarding.
B35: B10 | C35: An employee needs delegated spend | G35: =IFERROR(D35*E35*F35,0) | H35: T4 | I35: card | J35: [detection] Payroll headcount growth events, or second-signatory requests.
B36: B11 | C36: A first overseas supplier invoice arrives | G36: =IFERROR(D36*E36*F36,0) | H36: T3 | I36: fx | J36: [detection] First outbound cross-border payment per customer. Evidence held: 80% of SMEs report confusion at bank FX fees — the thinnest evidence base in the set and the biggest testable prize.
B37: B12 | C37: A first overseas customer payment is received | G37: =IFERROR(D37*E37*F37,0) | H37: T3 | I37: fx | J37: [detection] First inbound cross-border receipt per customer.
B39: PRODUCT DERIVATION
B40: Code | C40: Product | D40: lambda*c (won /cust/yr) | E40: Holding life L | F40: Derived pen | G40: Hardcode pen | H40: CALIBRATE: implied lambda*c | I40: One won moment per (customer-yrs) | J40: PENETRATION IN FORCE
B41: sav | C41: Instant-access savings | D41: =SUMIF($I$26:$I$37,$B41,$G$26:$G$37) | E41: ='Inputs'!$F$191 | F41: =IFERROR(D41*E41/(1+D41*E41),0) | G41: ='Inputs'!$F$32 | H41: =IFERROR(G41/((1-G41)*E41),"") | I41: =IFERROR(1/H41,"") | J41: =IF('1b. Demand & CEPs'!$C$5<>"LIVE",G41,IF(OR(D41=0,E41=0),G41,F41))
B42: dep | C42: Notice & fixed deposits | D42: =SUMIF($I$26:$I$37,$B42,$G$26:$G$37) | E42: ='Inputs'!$F$192 | F42: =IFERROR(D42*E42/(1+D42*E42),0) | G42: ='Inputs'!$F$34 | H42: =IFERROR(G42/((1-G42)*E42),"") | I42: =IFERROR(1/H42,"") | J42: =IF('1b. Demand & CEPs'!$C$5<>"LIVE",G42,IF(OR(D42=0,E42=0),G42,F42))
B43: od | C43: Business overdrafts | D43: =SUMIF($I$26:$I$37,$B43,$G$26:$G$37) | E43: ='Inputs'!$F$193 | F43: =IFERROR(D43*E43/(1+D43*E43),0) | G43: ='Inputs'!$F$36 | H43: =IFERROR(G43/((1-G43)*E43),"") | I43: =IFERROR(1/H43,"") | J43: =IF('1b. Demand & CEPs'!$C$5<>"LIVE",G43,IF(OR(D43=0,E43=0),G43,F43))
B44: loan | C44: Term loans & comm. mortgages | D44: =SUMIF($I$26:$I$37,$B44,$G$26:$G$37) | E44: ='Inputs'!$F$41 | F44: =IFERROR(D44*E44/(1+D44*E44),0) | G44: ='Inputs'!$F$39 | H44: =IFERROR(G44/((1-G44)*E44),"") | I44: =IFERROR(1/H44,"") | J44: =IF('1b. Demand & CEPs'!$C$5<>"LIVE",G44,IF(OR(D44=0,E44=0),G44,F44))
B45: af | C45: Asset finance | D45: =SUMIF($I$26:$I$37,$B45,$G$26:$G$37) | E45: ='Inputs'!$F$44 | F45: =IFERROR(D45*E45/(1+D45*E45),0) | G45: ='Inputs'!$F$42 | H45: =IFERROR(G45/((1-G45)*E45),"") | I45: =IFERROR(1/H45,"") | J45: =IF('1b. Demand & CEPs'!$C$5<>"LIVE",G45,IF(OR(D45=0,E45=0),G45,F45))
B46: inv | C46: Invoice finance | D46: =SUMIF($I$26:$I$37,$B46,$G$26:$G$37) | E46: ='Inputs'!$F$47 | F46: =IFERROR(D46*E46/(1+D46*E46),0) | G46: ='Inputs'!$F$45 | H46: =IFERROR(G46/((1-G46)*E46),"") | I46: =IFERROR(1/H46,"") | J46: =IF('1b. Demand & CEPs'!$C$5<>"LIVE",G46,IF(OR(D46=0,E46=0),G46,F46))
B47: card | C47: Business credit cards | D47: =SUMIF($I$26:$I$37,$B47,$G$26:$G$37) | E47: ='Inputs'!$F$194 | F47: =IFERROR(D47*E47/(1+D47*E47),0) | G47: ='Inputs'!$F$49 | H47: =IFERROR(G47/((1-G47)*E47),"") | I47: =IFERROR(1/H47,"") | J47: =IF('1b. Demand & CEPs'!$C$5<>"LIVE",G47,IF(OR(D47=0,E47=0),G47,F47))
B48: fx | C48: Payments & FX | D48: =SUMIF($I$26:$I$37,$B48,$G$26:$G$37) | E48: ='Inputs'!$F$195 | F48: =IFERROR(D48*E48/(1+D48*E48),0) | G48: ='Inputs'!$F$53 | H48: =IFERROR(G48/((1-G48)*E48),"") | I48: =IFERROR(1/H48,"") | J48: =IF('1b. Demand & CEPs'!$C$5<>"LIVE",G48,IF(OR(D48=0,E48=0),G48,F48))
B50: SELF-CHECKS
B51: 1. CALIBRATE reproduces the base | E51: =IF('1b. Demand & CEPs'!$C$5<>"CALIBRATE","n/a — mode is not CALIBRATE",IF(SUMPRODUCT(--(ROUND(J41:J48,9)<>ROUND(G41:G48,9)))=0,"PASS — every penetration equals its hardcode","FAIL")) | J51: CALIBRATE is diagnostic: it reports the implied event rate and changes no output. The layer must reproduce the model before it may change it.
B52: 2. Toggle OFF is output-identical to v1.2 | E52: =IF('1b. Demand & CEPs'!$C$5<>"OFF","n/a — mode is not OFF",IF(AND(SUMPRODUCT(--(J41:J48<>G41:G48))=0,'1b. Demand & CEPs'!$G$21='1b. Demand & CEPs'!$G$17),"PASS — outputs identical to v1.2","FAIL")) | J52: The clean base is untouched. This layer sits on top of it.
B53: 3. Every penetration in force is bounded (0,1] | E53: =IF(SUMPRODUCT(--(J41:J48>1))+SUMPRODUCT(--(J41:J48<=0))=0,"PASS","FAIL — a penetration is outside (0,1]") | J53: Guaranteed by the saturating form; asserted anyway.
B54: 4. Little's Law closes on acquisition | E54: =IF(ABS('1b. Demand & CEPs'!$G$18*'1b. Demand & CEPs'!$G$15-'1b. Demand & CEPs'!$G$17)<0.001,"PASS — won events x relationship life = customers","FAIL") | J54: The identity the whole layer rests on, checked against the model's own numbers.
B55: 5. Every CEP row carries an evidence tier | E55: =IF(COUNTBLANK(H9:H13)+COUNTBLANK(H26:H37)=0,"PASS","FAIL — a CEP row has no evidence tier") | J55: A blank tier or a blank cohort query means the row is a guess. The build refuses.
B56: 6. Products live in LIVE mode | E56: =IF('1b. Demand & CEPs'!$C$5<>"LIVE","n/a — mode is not LIVE",COUNTIF(J41:J48,"<>")-SUMPRODUCT(--(J41:J48=G41:G48))&" of 8 products deriving; the rest fall back to hardcodes") | J56: Products go live independently as the bank populates each one. Partial population is the expected state, not an error.
B57: 7. Acquisition cost does not double-count RM effort | E57: =IF('1b. Demand & CEPs'!$I$14=0,"n/a — cost to be present not yet populated",IF('1b. Demand & CEPs'!$I$14<'3. HR & Activity'!$H$56,"PASS — below the RM origination cost already in the model","CHECK — exceeds RM origination cost; confirm the four RM-sold products are not being priced twice")) | J57: The four RM-sold products already carry an acquisition cost on tab 3 rows 50-57. This layer prices the products that had none.
B59: STATED LIMITS
B60: • Selection bias: lambda must be the event rate among NON-holders. If holders experience the event more often — and the digital evidence says adopters are selected, not created — the derivation is biased upward. Where a bank can only measure the rate across all customers, say so on the row.
B61: • Presence and conversion are not separately identified from stock data alone. CALIBRATE recovers their product, not each one. Splitting them needs an experiment — which is the point: it names the test.
B62: • Family A event counts are catchment quantities (Companies House), not bank quantities.
B63: • Post-inducement retention (A5) is unevidenced in both directions. BCR wound up without publishing it.
B64: • Acquisition cost is a memo in v1.3. Posting it to the P&L is the next version, alongside the process-performance work on the Step 2 tabs.

Sheet 2. Revenues
B1: PRODUCT REVENUES — UNIT AND TOTAL
B2: Net interest margins measured against internal funds transfer prices (floating = Bank Rate; term = Bank Rate + premium).
B4: Product | C4: Units | D4: Avg balance /unit | E4: Customer rate | F4: FTP rate | G4: Margin % | H4: NII per unit | I4: Fees per unit | J4: Revenue per unit | K4: Total NII (£) | L4: Total fees (£) | M4: Total revenue (£)
B5: Business current accounts | C5: ='1. Customers'!$C$12 | D5: ='1. Customers'!$D$12 | E5: ='Inputs'!$F$58 | F5: ='Inputs'!$F$17 | G5: =F5-E5 | H5: =D5*G5 | I5: =12*'Inputs'!$F$59+'Inputs'!$F$60 | J5: =H5+I5 | K5: =H5*C5 | L5: =I5*C5 | M5: =J5*C5
B6: Instant-access savings | C6: ='1. Customers'!$C$13 | D6: ='1. Customers'!$D$13 | E6: ='Inputs'!$F$61 | F6: ='Inputs'!$F$17 | G6: =F6-E6 | H6: =D6*G6 | I6: =0 | J6: =H6+I6 | K6: =H6*C6 | L6: =I6*C6 | M6: =J6*C6
B7: Notice & fixed deposits | C7: ='1. Customers'!$C$14 | D7: ='1. Customers'!$D$14 | E7: ='Inputs'!$F$62 | F7: ='Inputs'!$F$18 | G7: =F7-E7 | H7: =D7*G7 | I7: =0 | J7: =H7+I7 | K7: =H7*C7 | L7: =I7*C7 | M7: =J7*C7
B8: Business overdrafts | C8: ='1. Customers'!$C$15 | D8: ='1. Customers'!$D$15 | E8: ='Inputs'!$F$63 | F8: ='Inputs'!$F$10 | G8: =E8-F8 | H8: =D8*G8 | I8: ='Inputs'!$F$64*'Inputs'!$F$37 | J8: =H8+I8 | K8: =H8*C8 | L8: =I8*C8 | M8: =J8*C8
B9: Term loans & comm. mortgages | C9: ='1. Customers'!$C$16 | D9: ='1. Customers'!$D$16 | E9: ='Inputs'!$F$65 | F9: ='Inputs'!$F$11 | G9: =E9-F9 | H9: =D9*G9 | I9: ='Inputs'!$F$66*'Inputs'!$F$40/'Inputs'!$F$41 | J9: =H9+I9 | K9: =H9*C9 | L9: =I9*C9 | M9: =J9*C9
B10: Asset finance | C10: ='1. Customers'!$C$17 | D10: ='1. Customers'!$D$17 | E10: ='Inputs'!$F$67 | F10: ='Inputs'!$F$11 | G10: =E10-F10 | H10: =D10*G10 | I10: =0 | J10: =H10+I10 | K10: =H10*C10 | L10: =I10*C10 | M10: =J10*C10
B11: Invoice finance | C11: ='1. Customers'!$C$18 | D11: ='1. Customers'!$D$18 | E11: ='Inputs'!$F$10+'Inputs'!$F$68 | F11: ='Inputs'!$F$10 | G11: =E11-F11 | H11: =D11*G11 | I11: ='Inputs'!$F$69*'Inputs'!$F$46*'Inputs'!$F$48 | J11: =H11+I11 | K11: =H11*C11 | L11: =I11*C11 | M11: =J11*C11
B12: Business credit cards | C12: ='1. Customers'!$C$19 | D12: ='1. Customers'!$D$19 | E12: ='Inputs'!$F$72 | F12: ='Inputs'!$F$10 | G12: =E12-F12 | H12: =D12*G12 | I12: ='Inputs'!$F$70*'Inputs'!$F$50*12+'Inputs'!$F$71 | J12: =H12+I12 | K12: =H12*C12 | L12: =I12*C12 | M12: =J12*C12
B13: Payments & FX | C13: ='1. Customers'!$C$20 | D13: ='1. Customers'!$D$20 | E13: =0 | F13: =0 | G13: =0 | H13: =D13*G13 | I13: ='Inputs'!$F$54*'Inputs'!$F$73+'Inputs'!$F$55*'Inputs'!$F$74 | J13: =H13+I13 | K13: =H13*C13 | L13: =I13*C13 | M13: =J13*C13
B14: TOTAL | K14: =SUM(K5:K13) | L14: =SUM(L5:L13) | M14: =SUM(M5:M13)
B16: Deposit products earn the spread between the transfer price and the rate paid; lending earns customer rate minus transfer price. Invoice finance service fees are charged on funded invoice value (≈8× funds in use).
B18: Memo — liquidity charge, already inside the deposit NII above (deposits × buffer × drag): | C18: =-'1. Customers'!$E$21*'Inputs'!$F$14*'Inputs'!$F$15
B19: Memo — behavioural deposit credit, already inside the deposit NII above (stable balances × credit): | C19: =('1. Customers'!$E$12+'1. Customers'!$E$13)*'Inputs'!$F$16

Sheet 3. HR & Activity
B1: STEP 2 — RUNNING COSTS: PEOPLE FROM ACTIVITY DRIVERS
B2: Every FTE is derived from transaction intensity (I) and customer load (L) — no headcount is assumed directly.
B4: Available hours per FTE per year | C4: ='Inputs'!$F$98*12 | E4: 147 hrs/month × 12
B5: Loaded hourly rate — relationship manager | C5: ='Inputs'!$F$99*(1+'Inputs'!$F$103)/'3. HR & Activity'!$C$4
B6: Loaded hourly rate — credit analyst | C6: ='Inputs'!$F$100*(1+'Inputs'!$F$103)/'3. HR & Activity'!$C$4
B7: Loaded hourly rate — service & operations | C7: ='Inputs'!$F$101*(1+'Inputs'!$F$103)/'3. HR & Activity'!$C$4
B9: ACTIVITY DRIVER TABLE (transaction intensity, I)
B10: Activity | C10: Product | D10: Role | E10: Driver volume /yr | F10: Hours per | G10: Total hours /yr | H10: Cost (£/yr) | I10: Flow (tab 9) | J10: Cost low (£/yr) | K10: Cost high (£/yr) | L10: Channel (scenario dimension) | M10: Process type | N10: Yield | O10: Attempts /yr | P10: Automation rate | Q10: BiC hours per | R10: BiC yield | S10: Benchmark source + tier | T10: £ gap to best in class
B11: Customer onboarding (KYC/AML, account setup) | C11: bca | D11: Service & ops | E11: ='1. Customers'!$C$8 | F11: ='Inputs'!$F$105 | G11: =O11*F11 | H11: =G11*'3. HR & Activity'!$C$7 | I11: CA-WP | J11: =H11*'Inputs'!$F$118 | K11: =H11*'Inputs'!$F$119 | L11: digital-amenable | M11: TRANSACTIONAL | N11: 1 | O11: =IF('Inputs'!$F$198<>"LIVE",E11,IF(M11<>"TRANSACTIONAL",E11,IF(OR(N11="",N11<=0),E11,E11/N11))) | T11: =IFERROR(IF(Q11="",0,O11*(F11-Q11)*'3. HR & Activity'!$C$7),0)+IFERROR(IF(OR(R11="",N11="",R11<=0,N11<=0),0,E11*(1/N11-1/R11)*F11*'3. HR & Activity'!$C$7),0)
B12: Current account servicing | C12: bca | D12: Service & ops | E12: ='1. Customers'!$C$12 | F12: ='Inputs'!$F$106 | G12: =O12*F12 | H12: =G12*'3. HR & Activity'!$C$7 | I12: CA-WP | J12: =H12*'Inputs'!$F$118 | K12: =H12*'Inputs'!$F$119 | L12: digital-amenable | M12: CONTINUOUS | O12: =IF('Inputs'!$F$198<>"LIVE",E12,IF(M12<>"TRANSACTIONAL",E12,IF(OR(N12="",N12<=0),E12,E12/N12))) | T12: =IFERROR(IF(Q12="",0,O12*(F12-Q12)*'3. HR & Activity'!$C$7),0)+IFERROR(IF(OR(R12="",N12="",R12<=0,N12<=0),0,E12*(1/N12-1/R12)*F12*'3. HR & Activity'!$C$7),0)
B13: Savings servicing | C13: sav | D13: Service & ops | E13: ='1. Customers'!$C$13 | F13: ='Inputs'!$F$107 | G13: =O13*F13 | H13: =G13*'3. HR & Activity'!$C$7 | I13: SV-WP | J13: =H13*'Inputs'!$F$118 | K13: =H13*'Inputs'!$F$119 | L13: digital-amenable | M13: CONTINUOUS | O13: =IF('Inputs'!$F$198<>"LIVE",E13,IF(M13<>"TRANSACTIONAL",E13,IF(OR(N13="",N13<=0),E13,E13/N13))) | T13: =IFERROR(IF(Q13="",0,O13*(F13-Q13)*'3. HR & Activity'!$C$7),0)+IFERROR(IF(OR(R13="",N13="",R13<=0,N13<=0),0,E13*(1/N13-1/R13)*F13*'3. HR & Activity'!$C$7),0)
B14: Deposit servicing | C14: dep | D14: Service & ops | E14: ='1. Customers'!$C$14 | F14: ='Inputs'!$F$108 | G14: =O14*F14 | H14: =G14*'3. HR & Activity'!$C$7 | I14: SV-WP | J14: =H14*'Inputs'!$F$118 | K14: =H14*'Inputs'!$F$119 | L14: digital-amenable | M14: CONTINUOUS | O14: =IF('Inputs'!$F$198<>"LIVE",E14,IF(M14<>"TRANSACTIONAL",E14,IF(OR(N14="",N14<=0),E14,E14/N14))) | T14: =IFERROR(IF(Q14="",0,O14*(F14-Q14)*'3. HR & Activity'!$C$7),0)+IFERROR(IF(OR(R14="",N14="",R14<=0,N14<=0),0,E14*(1/N14-1/R14)*F14*'3. HR & Activity'!$C$7),0)
B15: Overdraft reviews & renewals | C15: od | D15: Credit analyst | E15: ='1. Customers'!$C$15 | F15: ='Inputs'!$F$109 | G15: =O15*F15 | H15: =G15*'3. HR & Activity'!$C$6 | I15: LN-WP | J15: =H15*'Inputs'!$F$118 | K15: =H15*'Inputs'!$F$119 | L15: judgement | M15: CONTINUOUS | O15: =IF('Inputs'!$F$198<>"LIVE",E15,IF(M15<>"TRANSACTIONAL",E15,IF(OR(N15="",N15<=0),E15,E15/N15))) | T15: =IFERROR(IF(Q15="",0,O15*(F15-Q15)*'3. HR & Activity'!$C$6),0)+IFERROR(IF(OR(R15="",N15="",R15<=0,N15<=0),0,E15*(1/N15-1/R15)*F15*'3. HR & Activity'!$C$6),0)
B16: Term loan underwriting (new loans) | C16: loan | D16: Credit analyst | E16: ='1. Customers'!$C$16/'Inputs'!$F$41 | F16: ='Inputs'!$F$110 | G16: =O16*F16 | H16: =G16*'3. HR & Activity'!$C$6 | I16: LN-WP | J16: =H16*'Inputs'!$F$118 | K16: =H16*'Inputs'!$F$119 | L16: judgement | M16: TRANSACTIONAL | N16: 1 | O16: =IF('Inputs'!$F$198<>"LIVE",E16,IF(M16<>"TRANSACTIONAL",E16,IF(OR(N16="",N16<=0),E16,E16/N16))) | T16: =IFERROR(IF(Q16="",0,O16*(F16-Q16)*'3. HR & Activity'!$C$6),0)+IFERROR(IF(OR(R16="",N16="",R16<=0,N16<=0),0,E16*(1/N16-1/R16)*F16*'3. HR & Activity'!$C$6),0)
B17: Term loan annual reviews | C17: loan | D17: Credit analyst | E17: ='1. Customers'!$C$16 | F17: ='Inputs'!$F$111 | G17: =O17*F17 | H17: =G17*'3. HR & Activity'!$C$6 | I17: LN-WP | J17: =H17*'Inputs'!$F$118 | K17: =H17*'Inputs'!$F$119 | L17: judgement | M17: CONTINUOUS | O17: =IF('Inputs'!$F$198<>"LIVE",E17,IF(M17<>"TRANSACTIONAL",E17,IF(OR(N17="",N17<=0),E17,E17/N17))) | T17: =IFERROR(IF(Q17="",0,O17*(F17-Q17)*'3. HR & Activity'!$C$6),0)+IFERROR(IF(OR(R17="",N17="",R17<=0,N17<=0),0,E17*(1/N17-1/R17)*F17*'3. HR & Activity'!$C$6),0)
B18: Asset finance origination | C18: af | D18: Credit analyst | E18: ='1. Customers'!$C$17/'Inputs'!$F$44 | F18: ='Inputs'!$F$112 | G18: =O18*F18 | H18: =G18*'3. HR & Activity'!$C$6 | I18: LN-WP | J18: =H18*'Inputs'!$F$118 | K18: =H18*'Inputs'!$F$119 | L18: digital-amenable | M18: TRANSACTIONAL | N18: 1 | O18: =IF('Inputs'!$F$198<>"LIVE",E18,IF(M18<>"TRANSACTIONAL",E18,IF(OR(N18="",N18<=0),E18,E18/N18))) | T18: =IFERROR(IF(Q18="",0,O18*(F18-Q18)*'3. HR & Activity'!$C$6),0)+IFERROR(IF(OR(R18="",N18="",R18<=0,N18<=0),0,E18*(1/N18-1/R18)*F18*'3. HR & Activity'!$C$6),0)
B19: Invoice finance client onboarding | C19: inv | D19: Credit analyst | E19: ='1. Customers'!$C$18/'Inputs'!$F$47 | F19: ='Inputs'!$F$113 | G19: =O19*F19 | H19: =G19*'3. HR & Activity'!$C$6 | I19: LN-WP | J19: =H19*'Inputs'!$F$118 | K19: =H19*'Inputs'!$F$119 | L19: judgement | M19: TRANSACTIONAL | N19: 1 | O19: =IF('Inputs'!$F$198<>"LIVE",E19,IF(M19<>"TRANSACTIONAL",E19,IF(OR(N19="",N19<=0),E19,E19/N19))) | T19: =IFERROR(IF(Q19="",0,O19*(F19-Q19)*'3. HR & Activity'!$C$6),0)+IFERROR(IF(OR(R19="",N19="",R19<=0,N19<=0),0,E19*(1/N19-1/R19)*F19*'3. HR & Activity'!$C$6),0)
B20: Invoice finance monitoring | C20: inv | D20: Credit analyst | E20: ='1. Customers'!$C$18 | F20: ='Inputs'!$F$114*12 | G20: =O20*F20 | H20: =G20*'3. HR & Activity'!$C$6 | I20: LN-WP | J20: =H20*'Inputs'!$F$118 | K20: =H20*'Inputs'!$F$119 | L20: judgement | M20: CONTINUOUS | O20: =IF('Inputs'!$F$198<>"LIVE",E20,IF(M20<>"TRANSACTIONAL",E20,IF(OR(N20="",N20<=0),E20,E20/N20))) | T20: =IFERROR(IF(Q20="",0,O20*(F20-Q20)*'3. HR & Activity'!$C$6),0)+IFERROR(IF(OR(R20="",N20="",R20<=0,N20<=0),0,E20*(1/N20-1/R20)*F20*'3. HR & Activity'!$C$6),0)
B21: Card servicing | C21: card | D21: Service & ops | E21: ='1. Customers'!$C$19 | F21: ='Inputs'!$F$115 | G21: =O21*F21 | H21: =G21*'3. HR & Activity'!$C$7 | I21: CC-WP | J21: =H21*'Inputs'!$F$118 | K21: =H21*'Inputs'!$F$119 | L21: digital-amenable | M21: CONTINUOUS | O21: =IF('Inputs'!$F$198<>"LIVE",E21,IF(M21<>"TRANSACTIONAL",E21,IF(OR(N21="",N21<=0),E21,E21/N21))) | T21: =IFERROR(IF(Q21="",0,O21*(F21-Q21)*'3. HR & Activity'!$C$7),0)+IFERROR(IF(OR(R21="",N21="",R21<=0,N21<=0),0,E21*(1/N21-1/R21)*F21*'3. HR & Activity'!$C$7),0)
B22: Payments & FX support | C22: fx | D22: Service & ops | E22: ='1. Customers'!$C$20 | F22: ='Inputs'!$F$116 | G22: =O22*F22 | H22: =G22*'3. HR & Activity'!$C$7 | I22: PX-WP | J22: =H22*'Inputs'!$F$118 | K22: =H22*'Inputs'!$F$119 | L22: digital-amenable | M22: CONTINUOUS | O22: =IF('Inputs'!$F$198<>"LIVE",E22,IF(M22<>"TRANSACTIONAL",E22,IF(OR(N22="",N22<=0),E22,E22/N22))) | T22: =IFERROR(IF(Q22="",0,O22*(F22-Q22)*'3. HR & Activity'!$C$7),0)+IFERROR(IF(OR(R22="",N22="",R22<=0,N22<=0),0,E22*(1/N22-1/R22)*F22*'3. HR & Activity'!$C$7),0)
B23: Collections — overdrafts | C23: od | D23: Credit analyst | E23: ='1. Customers'!$C$15*'Inputs'!$F$117 | F23: ='Inputs'!$F$120 | G23: =O23*F23 | H23: =G23*'3. HR & Activity'!$C$6 | I23: LN-WP | J23: =H23*'Inputs'!$F$118 | K23: =H23*'Inputs'!$F$119 | L23: judgement | M23: CONTINUOUS | O23: =IF('Inputs'!$F$198<>"LIVE",E23,IF(M23<>"TRANSACTIONAL",E23,IF(OR(N23="",N23<=0),E23,E23/N23))) | T23: =IFERROR(IF(Q23="",0,O23*(F23-Q23)*'3. HR & Activity'!$C$6),0)+IFERROR(IF(OR(R23="",N23="",R23<=0,N23<=0),0,E23*(1/N23-1/R23)*F23*'3. HR & Activity'!$C$6),0)
B24: Collections — term loans | C24: loan | D24: Credit analyst | E24: ='1. Customers'!$C$16*'Inputs'!$F$117 | F24: ='Inputs'!$F$120 | G24: =O24*F24 | H24: =G24*'3. HR & Activity'!$C$6 | I24: LN-WP | J24: =H24*'Inputs'!$F$118 | K24: =H24*'Inputs'!$F$119 | L24: judgement | M24: CONTINUOUS | O24: =IF('Inputs'!$F$198<>"LIVE",E24,IF(M24<>"TRANSACTIONAL",E24,IF(OR(N24="",N24<=0),E24,E24/N24))) | T24: =IFERROR(IF(Q24="",0,O24*(F24-Q24)*'3. HR & Activity'!$C$6),0)+IFERROR(IF(OR(R24="",N24="",R24<=0,N24<=0),0,E24*(1/N24-1/R24)*F24*'3. HR & Activity'!$C$6),0)
B25: Collections — asset finance | C25: af | D25: Credit analyst | E25: ='1. Customers'!$C$17*'Inputs'!$F$117 | F25: ='Inputs'!$F$120 | G25: =O25*F25 | H25: =G25*'3. HR & Activity'!$C$6 | I25: LN-WP | J25: =H25*'Inputs'!$F$118 | K25: =H25*'Inputs'!$F$119 | L25: judgement | M25: CONTINUOUS | O25: =IF('Inputs'!$F$198<>"LIVE",E25,IF(M25<>"TRANSACTIONAL",E25,IF(OR(N25="",N25<=0),E25,E25/N25))) | T25: =IFERROR(IF(Q25="",0,O25*(F25-Q25)*'3. HR & Activity'!$C$6),0)+IFERROR(IF(OR(R25="",N25="",R25<=0,N25<=0),0,E25*(1/N25-1/R25)*F25*'3. HR & Activity'!$C$6),0)
B26: Collections — invoice finance | C26: inv | D26: Credit analyst | E26: ='1. Customers'!$C$18*'Inputs'!$F$117 | F26: ='Inputs'!$F$120 | G26: =O26*F26 | H26: =G26*'3. HR & Activity'!$C$6 | I26: LN-WP | J26: =H26*'Inputs'!$F$118 | K26: =H26*'Inputs'!$F$119 | L26: judgement | M26: CONTINUOUS | O26: =IF('Inputs'!$F$198<>"LIVE",E26,IF(M26<>"TRANSACTIONAL",E26,IF(OR(N26="",N26<=0),E26,E26/N26))) | T26: =IFERROR(IF(Q26="",0,O26*(F26-Q26)*'3. HR & Activity'!$C$6),0)+IFERROR(IF(OR(R26="",N26="",R26<=0,N26<=0),0,E26*(1/N26-1/R26)*F26*'3. HR & Activity'!$C$6),0)
B27: Collections — cards | C27: card | D27: Credit analyst | E27: ='1. Customers'!$C$19*'Inputs'!$F$117 | F27: ='Inputs'!$F$120 | G27: =O27*F27 | H27: =G27*'3. HR & Activity'!$C$6 | I27: CC-WP | J27: =H27*'Inputs'!$F$118 | K27: =H27*'Inputs'!$F$119 | L27: judgement | M27: CONTINUOUS | O27: =IF('Inputs'!$F$198<>"LIVE",E27,IF(M27<>"TRANSACTIONAL",E27,IF(OR(N27="",N27<=0),E27,E27/N27))) | T27: =IFERROR(IF(Q27="",0,O27*(F27-Q27)*'3. HR & Activity'!$C$6),0)+IFERROR(IF(OR(R27="",N27="",R27<=0,N27<=0),0,E27*(1/N27-1/R27)*F27*'3. HR & Activity'!$C$6),0)
B28: Collateral administration — term loans | C28: loan | D28: Credit analyst | E28: ='1. Customers'!$C$16 | F28: ='Inputs'!$F$121 | G28: =O28*F28 | H28: =G28*'3. HR & Activity'!$C$6 | I28: LN-WP | J28: =H28*'Inputs'!$F$118 | K28: =H28*'Inputs'!$F$119 | L28: digital-amenable | M28: CONTINUOUS | O28: =IF('Inputs'!$F$198<>"LIVE",E28,IF(M28<>"TRANSACTIONAL",E28,IF(OR(N28="",N28<=0),E28,E28/N28))) | T28: =IFERROR(IF(Q28="",0,O28*(F28-Q28)*'3. HR & Activity'!$C$6),0)+IFERROR(IF(OR(R28="",N28="",R28<=0,N28<=0),0,E28*(1/N28-1/R28)*F28*'3. HR & Activity'!$C$6),0)
B29: Collateral administration — asset finance | C29: af | D29: Credit analyst | E29: ='1. Customers'!$C$17 | F29: ='Inputs'!$F$121 | G29: =O29*F29 | H29: =G29*'3. HR & Activity'!$C$6 | I29: LN-WP | J29: =H29*'Inputs'!$F$118 | K29: =H29*'Inputs'!$F$119 | L29: digital-amenable | M29: CONTINUOUS | O29: =IF('Inputs'!$F$198<>"LIVE",E29,IF(M29<>"TRANSACTIONAL",E29,IF(OR(N29="",N29<=0),E29,E29/N29))) | T29: =IFERROR(IF(Q29="",0,O29*(F29-Q29)*'3. HR & Activity'!$C$6),0)+IFERROR(IF(OR(R29="",N29="",R29<=0,N29<=0),0,E29*(1/N29-1/R29)*F29*'3. HR & Activity'!$C$6),0)
B30: Collateral administration — invoice finance | C30: inv | D30: Credit analyst | E30: ='1. Customers'!$C$18 | F30: ='Inputs'!$F$121 | G30: =O30*F30 | H30: =G30*'3. HR & Activity'!$C$6 | I30: LN-WP | J30: =H30*'Inputs'!$F$118 | K30: =H30*'Inputs'!$F$119 | L30: digital-amenable | M30: CONTINUOUS | O30: =IF('Inputs'!$F$198<>"LIVE",E30,IF(M30<>"TRANSACTIONAL",E30,IF(OR(N30="",N30<=0),E30,E30/N30))) | T30: =IFERROR(IF(Q30="",0,O30*(F30-Q30)*'3. HR & Activity'!$C$6),0)+IFERROR(IF(OR(R30="",N30="",R30<=0,N30<=0),0,E30*(1/N30-1/R30)*F30*'3. HR & Activity'!$C$6),0)
B31: Recoveries & workout — term loans | C31: loan | D31: Credit analyst | E31: ='1. Customers'!$C$16*'Inputs'!$F$117 | F31: ='Inputs'!$F$122 | G31: =O31*F31 | H31: =G31*'3. HR & Activity'!$C$6 | I31: LN-WP | J31: =H31*'Inputs'!$F$118 | K31: =H31*'Inputs'!$F$119 | L31: judgement | M31: CONTINUOUS | O31: =IF('Inputs'!$F$198<>"LIVE",E31,IF(M31<>"TRANSACTIONAL",E31,IF(OR(N31="",N31<=0),E31,E31/N31))) | T31: =IFERROR(IF(Q31="",0,O31*(F31-Q31)*'3. HR & Activity'!$C$6),0)+IFERROR(IF(OR(R31="",N31="",R31<=0,N31<=0),0,E31*(1/N31-1/R31)*F31*'3. HR & Activity'!$C$6),0)
B32: Recoveries & workout — asset finance | C32: af | D32: Credit analyst | E32: ='1. Customers'!$C$17*'Inputs'!$F$117 | F32: ='Inputs'!$F$122 | G32: =O32*F32 | H32: =G32*'3. HR & Activity'!$C$6 | I32: LN-WP | J32: =H32*'Inputs'!$F$118 | K32: =H32*'Inputs'!$F$119 | L32: judgement | M32: CONTINUOUS | O32: =IF('Inputs'!$F$198<>"LIVE",E32,IF(M32<>"TRANSACTIONAL",E32,IF(OR(N32="",N32<=0),E32,E32/N32))) | T32: =IFERROR(IF(Q32="",0,O32*(F32-Q32)*'3. HR & Activity'!$C$6),0)+IFERROR(IF(OR(R32="",N32="",R32<=0,N32<=0),0,E32*(1/N32-1/R32)*F32*'3. HR & Activity'!$C$6),0)
B33: Recoveries & workout — invoice finance | C33: inv | D33: Credit analyst | E33: ='1. Customers'!$C$18*'Inputs'!$F$117 | F33: ='Inputs'!$F$122 | G33: =O33*F33 | H33: =G33*'3. HR & Activity'!$C$6 | I33: LN-WP | J33: =H33*'Inputs'!$F$118 | K33: =H33*'Inputs'!$F$119 | L33: judgement | M33: CONTINUOUS | O33: =IF('Inputs'!$F$198<>"LIVE",E33,IF(M33<>"TRANSACTIONAL",E33,IF(OR(N33="",N33<=0),E33,E33/N33))) | T33: =IFERROR(IF(Q33="",0,O33*(F33-Q33)*'3. HR & Activity'!$C$6),0)+IFERROR(IF(OR(R33="",N33="",R33<=0,N33<=0),0,E33*(1/N33-1/R33)*F33*'3. HR & Activity'!$C$6),0)
B35: FTE REQUIREMENT & COST (customer load, L)
B36: Role | D36: FTEs | E36: Salary (£) | H36: Total cost (£/yr)
B37: Relationship managers (portfolio-driven) | D37: ='1. Customers'!$C$5/'Inputs'!$F$25 | E37: ='Inputs'!$F$99 | H37: =D37*E37*(1+'Inputs'!$F$103)
B38: Credit analysts / underwriters (activity-driven) | D38: =SUMIF('3. HR & Activity'!$D$11:$D$33,"Credit analyst",'3. HR & Activity'!$G$11:$G$33)/'3. HR & Activity'!$C$4 | E38: ='Inputs'!$F$100 | H38: =D38*E38*(1+'Inputs'!$F$103)
B39: Service & operations (activity-driven) | D39: =SUMIF('3. HR & Activity'!$D$11:$D$33,"Service & ops",'3. HR & Activity'!$G$11:$G$33)/'3. HR & Activity'!$C$4 | E39: ='Inputs'!$F$101 | H39: =D39*E39*(1+'Inputs'!$F$103)
B40: Team managers (span-driven) | D40: =('3. HR & Activity'!$D$37+'3. HR & Activity'!$D$38+'3. HR & Activity'!$D$39)/'Inputs'!$F$104 | E40: ='Inputs'!$F$102 | H40: =D40*E40*(1+'Inputs'!$F$103)
B41: TOTAL OPERATING-UNIT STAFF | D41: ='3. HR & Activity'!$D$37+'3. HR & Activity'!$D$38+'3. HR & Activity'!$D$39+'3. HR & Activity'!$D$40 | H41: ='3. HR & Activity'!$H$37+'3. HR & Activity'!$H$38+'3. HR & Activity'!$H$39+'3. HR & Activity'!$H$40
B43: Loaded hourly rates spread salary + on-costs over available hours; activity costs therefore reconcile exactly to analyst and service payroll.
B45: THE RM SYSTEM — ORIGINATE / STEWARD / DEFEND (three activities, one system)
B46: RM time & cost — originate | D46: ='Inputs'!$F$163 | H46: ='3. HR & Activity'!$H$37*'Inputs'!$F$163
B47: RM time & cost — steward | D47: ='Inputs'!$F$164 | H47: ='3. HR & Activity'!$H$37*'Inputs'!$F$164
B48: RM time & cost — defend | D48: ='Inputs'!$F$165 | H48: ='3. HR & Activity'!$H$37*'Inputs'!$F$165
B50: 1. ORIGINATE — acquisition cost attributed per origination by relative effort
B51: Product | D51: Originations / renewals p.a. | E51: Effort weight | F51: Weighted volume | G51: RM cost attributed (£/yr) | H51: Cost per unit on book (£/yr)
B52: Term loans (new) | D52: ='1. Customers'!$C$16/'Inputs'!$F$41 | E52: ='Inputs'!$F$159 | F52: =D52*E52 | G52: =F52/SUM(F52:F55)*'3. HR & Activity'!$H$46 | H52: =G52/'1. Customers'!$C$16
B53: Asset finance (new) | D53: ='1. Customers'!$C$17/'Inputs'!$F$44 | E53: ='Inputs'!$F$160 | F53: =D53*E53 | G53: =F53/SUM(F52:F55)*'3. HR & Activity'!$H$46 | H53: =G53/'1. Customers'!$C$17
B54: Invoice finance (new clients) | D54: ='1. Customers'!$C$18/'Inputs'!$F$47 | E54: ='Inputs'!$F$161 | F54: =D54*E54 | G54: =F54/SUM(F52:F55)*'3. HR & Activity'!$H$46 | H54: =G54/'1. Customers'!$C$18
B55: Overdrafts (annual renewals) | D55: ='1. Customers'!$C$15 | E55: ='Inputs'!$F$162 | F55: =D55*E55 | G55: =F55/SUM(F52:F55)*'3. HR & Activity'!$H$46 | H55: =G55/'1. Customers'!$C$15
B56: TOTAL RM ORIGINATION COST ATTRIBUTED | G56: =SUM(G52:G55)
B57: RM origination cost per weighted origination | G57: ='3. HR & Activity'!$H$46/SUM(F52:F55) | H57: The return-on-RM-time yardstick: compare to lifetime contribution of the products sold
B59: 2. STEWARD — attributed to lending products pro-rata balances; pays back through lower PDs (tab 5)
B60: Product | D60: Balances (£) | E60: Share | G60: Stewardship cost (£/yr) | H60: Per unit (£/yr)
B61: Overdrafts | D61: ='1. Customers'!$E$15 | E61: ='1. Customers'!$E$15/('1. Customers'!$E$15+'1. Customers'!$E$16+'1. Customers'!$E$17+'1. Customers'!$E$18) | G61: =E61*'3. HR & Activity'!$H$47 | H61: =G61/'1. Customers'!$C$15
B62: Term loans | D62: ='1. Customers'!$E$16 | E62: ='1. Customers'!$E$16/('1. Customers'!$E$15+'1. Customers'!$E$16+'1. Customers'!$E$17+'1. Customers'!$E$18) | G62: =E62*'3. HR & Activity'!$H$47 | H62: =G62/'1. Customers'!$C$16
B63: Asset finance | D63: ='1. Customers'!$E$17 | E63: ='1. Customers'!$E$17/('1. Customers'!$E$15+'1. Customers'!$E$16+'1. Customers'!$E$17+'1. Customers'!$E$18) | G63: =E63*'3. HR & Activity'!$H$47 | H63: =G63/'1. Customers'!$C$17
B64: Invoice finance | D64: ='1. Customers'!$E$18 | E64: ='1. Customers'!$E$18/('1. Customers'!$E$15+'1. Customers'!$E$16+'1. Customers'!$E$17+'1. Customers'!$E$18) | G64: =E64*'3. HR & Activity'!$H$47 | H64: =G64/'1. Customers'!$C$18
B65: Memo: expected losses avoided by stewardship (tab 5 PD reduction) | G65: =('1. Customers'!$E$15*'Inputs'!$F$77*'Inputs'!$F$78+'1. Customers'!$E$16*'Inputs'!$F$79*'Inputs'!$F$80+'1. Customers'!$E$17*'Inputs'!$F$81*'Inputs'!$F$82+'1. Customers'!$E$18*'Inputs'!$F$83*'Inputs'!$F$84)*'Inputs'!$F$167*'Inputs'!$F$166 | H65: Compare to stewardship cost above — excludes unpriced benefits (recovery quality, origination signals)
B67: 3. DEFEND — tested retention spend, held at centre level (not product-allocated)
B68: Defence cost (RM time on retention) | G68: ='3. HR & Activity'!$H$48
B69: Customers defended per year (churn reduction — validate with holdouts) | G69: ='1. Customers'!$C$7
B70: Value of defended relationships: see memo under the bridge on tab 6 (contribution × remaining life)
B72: HEAD-OFFICE PROCESS REGISTER (Step 2, cont. — the processes inside the head-office pools)
B73: Every process below is already named in the tab 9 operational model; none had a cost row. NOTE: churn-replacement acquisition marketing is already carved from the corporate pool as cac_new (v1.3) and attributed on tab 4 — the mental-availability row here is for entry-point presence spend NOT already in cac_new, or it double-carves. Five carry the unit costs already in Inputs section G2, so they are live on build. The rest ship with a blank unit cost, contribute nothing, and leave the residual exactly where v1.3 left it. Naming one moves pounds from 'unallocated joint costs' to 'attributed' — the total never moves.
B74: Process | C74: Pool | D74: Driver | E74: Driver volume /yr | F74: Unit cost (£) | H74: Cost (£/yr) | I74: Flow (tab 9) | J74: Accountable owner | K74: Stage | Q74: BiC unit cost (£) | S74: Benchmark source + tier | T74: £ gap to best in class
B75: KYC & financial crime (new-customer onboarding) | C75: risk | D75: onboardings | E75: ='1. Customers'!$C$8 | F75: ='Inputs'!$F$134 | H75: =IFERROR(E75*F75,0) | I75: CA-WP | J75: Financial crime ops | K75: FULFILMENT | T75: =IFERROR(IF(OR(Q75="",F75=""),0,E75*(F75-Q75)),0)
B76: KYC refresh & ongoing screening | C76: risk | D76: customers | E76: ='1. Customers'!$C$4 | F76: ='Inputs'!$F$135 | H76: =IFERROR(E76*F76,0) | I76: S1 | J76: Financial crime ops | K76: FULFILMENT | T76: =IFERROR(IF(OR(Q76="",F76=""),0,E76*(F76-Q76)),0)
B77: Payments operations & processing | C77: tech | D77: current accounts | E77: ='1. Customers'!$C$12 | F77: ='Inputs'!$F$137 | H77: =IFERROR(E77*F77,0) | I77: CA-PP1 | J77: Payments ops | K77: FULFILMENT | T77: =IFERROR(IF(OR(Q77="",F77=""),0,E77*(F77-Q77)),0)
B78: Core banking system | C78: tech | D78: accounts on ledger | E78: ='1. Customers'!$C$24 | F78: ='Inputs'!$F$138 | H78: =IFERROR(E78*F78,0) | I78: E1 | J78: Technology | K78: ENABLING | T78: =IFERROR(IF(OR(Q78="",F78=""),0,E78*(F78-Q78)),0)
B79: Credit systems & portfolio monitoring | C79: tech | D79: live credit facilities | E79: ='1. Customers'!$C$25 | F79: ='Inputs'!$F$139 | H79: =IFERROR(E79*F79,0) | I79: LN-WP | J79: Credit risk | K79: FULFILMENT | T79: =IFERROR(IF(OR(Q79="",F79=""),0,E79*(F79-Q79)),0)
B80: Party reference data | C80: tech | D80: customers | E80: ='1. Customers'!$C$4 | H80: =IFERROR(E80*F80,0) | I80: I1 | J80: Data management | K80: ENABLING | T80: =IFERROR(IF(OR(Q80="",F80=""),0,E80*(F80-Q80)),0)
B81: Product directory & pricing | C81: corp | D81: products x price points | E81: ='1. Customers'!$C$4 | H81: =IFERROR(E81*F81,0) | I81: I2 | J81: Product management | K81: DEMAND | T81: =IFERROR(IF(OR(Q81="",F81=""),0,E81*(F81-Q81)),0)
B82: Regulatory compliance & reporting | C82: risk | D82: customers | E82: ='1. Customers'!$C$4 | H82: =IFERROR(E82*F82,0) | I82: S2 | J82: Compliance | K82: ENABLING | T82: =IFERROR(IF(OR(Q82="",F82=""),0,E82*(F82-Q82)),0)
B83: Sanctions screening / CDD | C83: risk | D83: payments screened | E83: ='1. Customers'!$C$20*'Inputs'!$F$55 | H83: =IFERROR(E83*F83,0) | I83: S1 | J83: Financial crime ops | K83: FULFILMENT | T83: =IFERROR(IF(OR(Q83="",F83=""),0,E83*(F83-Q83)),0)
B84: Card scheme & merchant relations | C84: tech | D84: cards | E84: ='1. Customers'!$C$19 | H84: =IFERROR(E84*F84,0) | I84: CC-PP1 | J84: Cards | K84: FULFILMENT | T84: =IFERROR(IF(OR(Q84="",F84=""),0,E84*(F84-Q84)),0)
B85: Operational risk | C85: risk | D85: customers | E85: ='1. Customers'!$C$4 | H85: =IFERROR(E85*F85,0) | I85: S4 | J85: Operational risk | K85: ENABLING | T85: =IFERROR(IF(OR(Q85="",F85=""),0,E85*(F85-Q85)),0)
B86: Customer access entitlement / authentication | C86: tech | D86: customers | E86: ='1. Customers'!$C$4 | H86: =IFERROR(E86*F86,0) | I86: E4 | J86: Technology | K86: ENABLING | T86: =IFERROR(IF(OR(Q86="",F86=""),0,E86*(F86-Q86)),0)
B87: Financial message gateway (Open Banking / API) | C87: tech | D87: accounts on ledger | E87: ='1. Customers'!$C$24 | H87: =IFERROR(E87*F87,0) | I87: E2 | J87: Technology | K87: ENABLING | T87: =IFERROR(IF(OR(Q87="",F87=""),0,E87*(F87-Q87)),0)
B88: Document & contract management | C88: tech | D88: live credit facilities | E88: ='1. Customers'!$C$25 | H88: =IFERROR(E88*F88,0) | I88: E3 | J88: Technology | K88: ENABLING | T88: =IFERROR(IF(OR(Q88="",F88=""),0,E88*(F88-Q88)),0)
B89: Reconciliation | C89: tech | D89: accounts on ledger | E89: ='1. Customers'!$C$24 | H89: =IFERROR(E89*F89,0) | I89: I3 | J89: Finance ops | K89: ENABLING | T89: =IFERROR(IF(OR(Q89="",F89=""),0,E89*(F89-Q89)),0)
B90: Position keeping (nostro / vostro) | C90: tech | D90: international payments | E90: ='1. Customers'!$C$20*'Inputs'!$F$55 | H90: =IFERROR(E90*F90,0) | I90: PX-PP1 | J90: Treasury | K90: FULFILMENT | T90: =IFERROR(IF(OR(Q90="",F90=""),0,E90*(F90-Q90)),0)
B91: Corporate treasury / ALM | C91: corp | D91: total balances | E91: ='1. Customers'!$E$21/1000000 | H91: =IFERROR(E91*F91,0) | I91: S3 | J91: Treasury | K91: ENABLING | T91: =IFERROR(IF(OR(Q91="",F91=""),0,E91*(F91-Q91)),0)
B92: Finance / general ledger | C92: corp | D92: customers | E92: ='1. Customers'!$C$4 | H92: =IFERROR(E92*F92,0) | I92: S2 | J92: Finance | K92: ENABLING | T92: =IFERROR(IF(OR(Q92="",F92=""),0,E92*(F92-Q92)),0)
B93: Fraud resolution | C93: risk | D93: current accounts | E93: ='1. Customers'!$C$12 | H93: =IFERROR(E93*F93,0) | I93: CA-WP | J93: Fraud ops | K93: FULFILMENT | T93: =IFERROR(IF(OR(Q93="",F93=""),0,E93*(F93-Q93)),0)
B94: Correspondence / notifications | C94: tech | D94: customers | E94: ='1. Customers'!$C$4 | H94: =IFERROR(E94*F94,0) | I94: CP1 | J94: Service & ops | K94: FULFILMENT | T94: =IFERROR(IF(OR(Q94="",F94=""),0,E94*(F94-Q94)),0)
B95: Detection rules for cross-holding entry points (CEP B1/B3/B9/B11/B12) | C95: tech | D95: customers | E95: ='1. Customers'!$C$4 | H95: =IFERROR(E95*F95,0) | I95: I1 | J95: Data management | K95: DEMAND | T95: =IFERROR(IF(OR(Q95="",F95=""),0,E95*(F95-Q95)),0)
B96: Mental-availability spend at entry points NOT already in cac_new (CEP A1/A3/A4) | C96: corp | D96: catchment businesses | E96: ='Inputs'!$F$21 | H96: =IFERROR(E96*F96,0) | I96: CP1 | J96: Marketing | K96: DEMAND | T96: =IFERROR(IF(OR(Q96="",F96=""),0,E96*(F96-Q96)),0)
B97: TOTAL NAMED HEAD-OFFICE PROCESS COST | H97: =SUM(H75:H96) | T97: =SUM(T75:T96)
B98: …of which technology pool | H98: =SUMIF('3. HR & Activity'!$C$75:$C$96,"tech",'3. HR & Activity'!$H$75:$H$96)
B99: …of which risk pool | H99: =SUMIF('3. HR & Activity'!$C$75:$C$96,"risk",'3. HR & Activity'!$H$75:$H$96)
B100: …of which corporate pool | H100: =SUMIF('3. HR & Activity'!$C$75:$C$96,"corp",'3. HR & Activity'!$H$75:$H$96)
B101: Activity-block gap to best in class (operating unit) | T101: =SUM(T11:T33)

Sheet 3b. Process Index
B1: PROCESS INDEX — WHICH PROCESS MOVES WHICH NUMBER
B2: Derived view. No assumptions live here. Every process in the model, with the flow it belongs to, the number it moves, its cost, and its gap to best in class. Filter the 'moves' column to answer 'what do I improve to change this number?'. Grouping is by the flow and product tags the model already carries, not by hand-maintained cell references — tags are load-bearing, cell references rot.
B4: Process | C4: Block | D4: Product | E4: Flow | F4: Accountable owner | G4: Moves these numbers | H4: Cost (£/yr) | I4: £ gap to BiC
B5: Customer onboarding (KYC/AML, account setup) | C5: operating unit | D5: bca | E5: CA-WP | F5: ='3. HR & Activity'!$D$11 | G5: BCA volumes · payments income · fraud cost | H5: ='3. HR & Activity'!$H$11 | I5: ='3. HR & Activity'!$T$11
B6: Current account servicing | C6: operating unit | D6: bca | E6: CA-WP | F6: ='3. HR & Activity'!$D$12 | G6: BCA volumes · payments income · fraud cost | H6: ='3. HR & Activity'!$H$12 | I6: ='3. HR & Activity'!$T$12
B7: Savings servicing | C7: operating unit | D7: sav | E7: SV-WP | F7: ='3. HR & Activity'!$D$13 | G7: Savings balances · deposit NII | H7: ='3. HR & Activity'!$H$13 | I7: ='3. HR & Activity'!$T$13
B8: Deposit servicing | C8: operating unit | D8: dep | E8: SV-WP | F8: ='3. HR & Activity'!$D$14 | G8: Term deposit balances · deposit NII | H8: ='3. HR & Activity'!$H$14 | I8: ='3. HR & Activity'!$T$14
B9: Overdraft reviews & renewals | C9: operating unit | D9: od | E9: LN-WP | F9: ='3. HR & Activity'!$D$15 | G9: Overdraft balances · overdraft income · cost of risk | H9: ='3. HR & Activity'!$H$15 | I9: ='3. HR & Activity'!$T$15
B10: Term loan underwriting (new loans) | C10: operating unit | D10: loan | E10: LN-WP | F10: ='3. HR & Activity'!$D$16 | G10: Loan balances · loan NII · cost of risk · RWA | H10: ='3. HR & Activity'!$H$16 | I10: ='3. HR & Activity'!$T$16
B11: Term loan annual reviews | C11: operating unit | D11: loan | E11: LN-WP | F11: ='3. HR & Activity'!$D$17 | G11: Loan balances · loan NII · cost of risk · RWA | H11: ='3. HR & Activity'!$H$17 | I11: ='3. HR & Activity'!$T$17
B12: Asset finance origination | C12: operating unit | D12: af | E12: LN-WP | F12: ='3. HR & Activity'!$D$18 | G12: Asset finance balances · AF yield · RWA | H12: ='3. HR & Activity'!$H$18 | I12: ='3. HR & Activity'!$T$18
B13: Invoice finance client onboarding | C13: operating unit | D13: inv | E13: LN-WP | F13: ='3. HR & Activity'!$D$19 | G13: Invoice finance funds in use · discount + service fees | H13: ='3. HR & Activity'!$H$19 | I13: ='3. HR & Activity'!$T$19
B14: Invoice finance monitoring | C14: operating unit | D14: inv | E14: LN-WP | F14: ='3. HR & Activity'!$D$20 | G14: Invoice finance funds in use · discount + service fees | H14: ='3. HR & Activity'!$H$20 | I14: ='3. HR & Activity'!$T$20
B15: Card servicing | C15: operating unit | D15: card | E15: CC-WP | F15: ='3. HR & Activity'!$D$21 | G15: Card balances · interchange · card fees | H15: ='3. HR & Activity'!$H$21 | I15: ='3. HR & Activity'!$T$21
B16: Payments & FX support | C16: operating unit | D16: fx | E16: PX-WP | F16: ='3. HR & Activity'!$D$22 | G16: FX volume · FX margin · payment fees | H16: ='3. HR & Activity'!$H$22 | I16: ='3. HR & Activity'!$T$22
B17: Collections — overdrafts | C17: operating unit | D17: od | E17: LN-WP | F17: ='3. HR & Activity'!$D$23 | G17: Overdraft balances · overdraft income · cost of risk | H17: ='3. HR & Activity'!$H$23 | I17: ='3. HR & Activity'!$T$23
B18: Collections — term loans | C18: operating unit | D18: loan | E18: LN-WP | F18: ='3. HR & Activity'!$D$24 | G18: Loan balances · loan NII · cost of risk · RWA | H18: ='3. HR & Activity'!$H$24 | I18: ='3. HR & Activity'!$T$24
B19: Collections — asset finance | C19: operating unit | D19: af | E19: LN-WP | F19: ='3. HR & Activity'!$D$25 | G19: Asset finance balances · AF yield · RWA | H19: ='3. HR & Activity'!$H$25 | I19: ='3. HR & Activity'!$T$25
B20: Collections — invoice finance | C20: operating unit | D20: inv | E20: LN-WP | F20: ='3. HR & Activity'!$D$26 | G20: Invoice finance funds in use · discount + service fees | H20: ='3. HR & Activity'!$H$26 | I20: ='3. HR & Activity'!$T$26
B21: Collections — cards | C21: operating unit | D21: card | E21: CC-WP | F21: ='3. HR & Activity'!$D$27 | G21: Card balances · interchange · card fees | H21: ='3. HR & Activity'!$H$27 | I21: ='3. HR & Activity'!$T$27
B22: Collateral administration — term loans | C22: operating unit | D22: loan | E22: LN-WP | F22: ='3. HR & Activity'!$D$28 | G22: Loan balances · loan NII · cost of risk · RWA | H22: ='3. HR & Activity'!$H$28 | I22: ='3. HR & Activity'!$T$28
B23: Collateral administration — asset finance | C23: operating unit | D23: af | E23: LN-WP | F23: ='3. HR & Activity'!$D$29 | G23: Asset finance balances · AF yield · RWA | H23: ='3. HR & Activity'!$H$29 | I23: ='3. HR & Activity'!$T$29
B24: Collateral administration — invoice finance | C24: operating unit | D24: inv | E24: LN-WP | F24: ='3. HR & Activity'!$D$30 | G24: Invoice finance funds in use · discount + service fees | H24: ='3. HR & Activity'!$H$30 | I24: ='3. HR & Activity'!$T$30
B25: Recoveries & workout — term loans | C25: operating unit | D25: loan | E25: LN-WP | F25: ='3. HR & Activity'!$D$31 | G25: Loan balances · loan NII · cost of risk · RWA | H25: ='3. HR & Activity'!$H$31 | I25: ='3. HR & Activity'!$T$31
B26: Recoveries & workout — asset finance | C26: operating unit | D26: af | E26: LN-WP | F26: ='3. HR & Activity'!$D$32 | G26: Asset finance balances · AF yield · RWA | H26: ='3. HR & Activity'!$H$32 | I26: ='3. HR & Activity'!$T$32
B27: Recoveries & workout — invoice finance | C27: operating unit | D27: inv | E27: LN-WP | F27: ='3. HR & Activity'!$D$33 | G27: Invoice finance funds in use · discount + service fees | H27: ='3. HR & Activity'!$H$33 | I27: ='3. HR & Activity'!$T$33
B28: KYC & financial crime (new-customer onboarding) | C28: head office | D28: risk | E28: CA-WP | F28: Financial crime ops | G28: Cost:income · operating cost per customer | H28: ='3. HR & Activity'!$H$75 | I28: ='3. HR & Activity'!$T$75
B29: KYC refresh & ongoing screening | C29: head office | D29: risk | E29: S1 | F29: Financial crime ops | G29: Cost:income · operating cost per customer | H29: ='3. HR & Activity'!$H$76 | I29: ='3. HR & Activity'!$T$76
B30: Payments operations & processing | C30: head office | D30: tech | E30: CA-PP1 | F30: Payments ops | G30: Cost:income · operating cost per customer | H30: ='3. HR & Activity'!$H$77 | I30: ='3. HR & Activity'!$T$77
B31: Core banking system | C31: head office | D31: tech | E31: E1 | F31: Technology | G31: Cost:income · operating cost per customer | H31: ='3. HR & Activity'!$H$78 | I31: ='3. HR & Activity'!$T$78
B32: Credit systems & portfolio monitoring | C32: head office | D32: tech | E32: LN-WP | F32: Credit risk | G32: Cost:income · operating cost per customer | H32: ='3. HR & Activity'!$H$79 | I32: ='3. HR & Activity'!$T$79
B33: Party reference data | C33: head office | D33: tech | E33: I1 | F33: Data management | G33: Cost:income · operating cost per customer | H33: ='3. HR & Activity'!$H$80 | I33: ='3. HR & Activity'!$T$80
B34: Product directory & pricing | C34: head office | D34: corp | E34: I2 | F34: Product management | G34: Cost:income · operating cost per customer · acquisition | H34: ='3. HR & Activity'!$H$81 | I34: ='3. HR & Activity'!$T$81
B35: Regulatory compliance & reporting | C35: head office | D35: risk | E35: S2 | F35: Compliance | G35: Cost:income · operating cost per customer | H35: ='3. HR & Activity'!$H$82 | I35: ='3. HR & Activity'!$T$82
B36: Sanctions screening / CDD | C36: head office | D36: risk | E36: S1 | F36: Financial crime ops | G36: Cost:income · operating cost per customer | H36: ='3. HR & Activity'!$H$83 | I36: ='3. HR & Activity'!$T$83
B37: Card scheme & merchant relations | C37: head office | D37: tech | E37: CC-PP1 | F37: Cards | G37: Cost:income · operating cost per customer | H37: ='3. HR & Activity'!$H$84 | I37: ='3. HR & Activity'!$T$84
B38: Operational risk | C38: head office | D38: risk | E38: S4 | F38: Operational risk | G38: Cost:income · operating cost per customer | H38: ='3. HR & Activity'!$H$85 | I38: ='3. HR & Activity'!$T$85
B39: Customer access entitlement / authentication | C39: head office | D39: tech | E39: E4 | F39: Technology | G39: Cost:income · operating cost per customer | H39: ='3. HR & Activity'!$H$86 | I39: ='3. HR & Activity'!$T$86
B40: Financial message gateway (Open Banking / API) | C40: head office | D40: tech | E40: E2 | F40: Technology | G40: Cost:income · operating cost per customer | H40: ='3. HR & Activity'!$H$87 | I40: ='3. HR & Activity'!$T$87
B41: Document & contract management | C41: head office | D41: tech | E41: E3 | F41: Technology | G41: Cost:income · operating cost per customer | H41: ='3. HR & Activity'!$H$88 | I41: ='3. HR & Activity'!$T$88
B42: Reconciliation | C42: head office | D42: tech | E42: I3 | F42: Finance ops | G42: Cost:income · operating cost per customer | H42: ='3. HR & Activity'!$H$89 | I42: ='3. HR & Activity'!$T$89
B43: Position keeping (nostro / vostro) | C43: head office | D43: tech | E43: PX-PP1 | F43: Treasury | G43: Cost:income · operating cost per customer | H43: ='3. HR & Activity'!$H$90 | I43: ='3. HR & Activity'!$T$90
B44: Corporate treasury / ALM | C44: head office | D44: corp | E44: S3 | F44: Treasury | G44: Cost:income · operating cost per customer | H44: ='3. HR & Activity'!$H$91 | I44: ='3. HR & Activity'!$T$91
B45: Finance / general ledger | C45: head office | D45: corp | E45: S2 | F45: Finance | G45: Cost:income · operating cost per customer | H45: ='3. HR & Activity'!$H$92 | I45: ='3. HR & Activity'!$T$92
B46: Fraud resolution | C46: head office | D46: risk | E46: CA-WP | F46: Fraud ops | G46: Cost:income · operating cost per customer | H46: ='3. HR & Activity'!$H$93 | I46: ='3. HR & Activity'!$T$93
B47: Correspondence / notifications | C47: head office | D47: tech | E47: CP1 | F47: Service & ops | G47: Cost:income · operating cost per customer | H47: ='3. HR & Activity'!$H$94 | I47: ='3. HR & Activity'!$T$94
B48: Detection rules for cross-holding entry points (CEP B1/B3/B9/B11/B12) | C48: head office | D48: tech | E48: I1 | F48: Data management | G48: Cost:income · operating cost per customer · acquisition | H48: ='3. HR & Activity'!$H$95 | I48: ='3. HR & Activity'!$T$95
B49: Mental-availability spend at entry points NOT already in cac_new (CEP A1/A3/A4) | C49: head office | D49: corp | E49: CP1 | F49: Marketing | G49: Cost:income · operating cost per customer · acquisition | H49: ='3. HR & Activity'!$H$96 | I49: ='3. HR & Activity'!$T$96
B51: RANKED — LARGEST GAP TO BEST IN CLASS
B52: Empty until benchmark cells are populated on tab 3. That is the intended shipping state.
B53: Rank | C53: Process | I53: £ gap to BiC
B54: 1 | C54: =IFERROR(IF(LARGE($I$5:$I$49,1)<=0,"—",INDEX($B$5:$B$49,MATCH(LARGE($I$5:$I$49,1),$I$5:$I$49,0))),"—") | I54: =IFERROR(IF(LARGE($I$5:$I$49,1)<=0,"",LARGE($I$5:$I$49,1)),"")
B55: 2 | C55: =IFERROR(IF(LARGE($I$5:$I$49,2)<=0,"—",INDEX($B$5:$B$49,MATCH(LARGE($I$5:$I$49,2),$I$5:$I$49,0))),"—") | I55: =IFERROR(IF(LARGE($I$5:$I$49,2)<=0,"",LARGE($I$5:$I$49,2)),"")
B56: 3 | C56: =IFERROR(IF(LARGE($I$5:$I$49,3)<=0,"—",INDEX($B$5:$B$49,MATCH(LARGE($I$5:$I$49,3),$I$5:$I$49,0))),"—") | I56: =IFERROR(IF(LARGE($I$5:$I$49,3)<=0,"",LARGE($I$5:$I$49,3)),"")
B57: 4 | C57: =IFERROR(IF(LARGE($I$5:$I$49,4)<=0,"—",INDEX($B$5:$B$49,MATCH(LARGE($I$5:$I$49,4),$I$5:$I$49,0))),"—") | I57: =IFERROR(IF(LARGE($I$5:$I$49,4)<=0,"",LARGE($I$5:$I$49,4)),"")
B58: 5 | C58: =IFERROR(IF(LARGE($I$5:$I$49,5)<=0,"—",INDEX($B$5:$B$49,MATCH(LARGE($I$5:$I$49,5),$I$5:$I$49,0))),"—") | I58: =IFERROR(IF(LARGE($I$5:$I$49,5)<=0,"",LARGE($I$5:$I$49,5)),"")
B59: 6 | C59: =IFERROR(IF(LARGE($I$5:$I$49,6)<=0,"—",INDEX($B$5:$B$49,MATCH(LARGE($I$5:$I$49,6),$I$5:$I$49,0))),"—") | I59: =IFERROR(IF(LARGE($I$5:$I$49,6)<=0,"",LARGE($I$5:$I$49,6)),"")
B60: 7 | C60: =IFERROR(IF(LARGE($I$5:$I$49,7)<=0,"—",INDEX($B$5:$B$49,MATCH(LARGE($I$5:$I$49,7),$I$5:$I$49,0))),"—") | I60: =IFERROR(IF(LARGE($I$5:$I$49,7)<=0,"",LARGE($I$5:$I$49,7)),"")
B61: 8 | C61: =IFERROR(IF(LARGE($I$5:$I$49,8)<=0,"—",INDEX($B$5:$B$49,MATCH(LARGE($I$5:$I$49,8),$I$5:$I$49,0))),"—") | I61: =IFERROR(IF(LARGE($I$5:$I$49,8)<=0,"",LARGE($I$5:$I$49,8)),"")
B62: 9 | C62: =IFERROR(IF(LARGE($I$5:$I$49,9)<=0,"—",INDEX($B$5:$B$49,MATCH(LARGE($I$5:$I$49,9),$I$5:$I$49,0))),"—") | I62: =IFERROR(IF(LARGE($I$5:$I$49,9)<=0,"",LARGE($I$5:$I$49,9)),"")
B63: 10 | C63: =IFERROR(IF(LARGE($I$5:$I$49,10)<=0,"—",INDEX($B$5:$B$49,MATCH(LARGE($I$5:$I$49,10),$I$5:$I$49,0))),"—") | I63: =IFERROR(IF(LARGE($I$5:$I$49,10)<=0,"",LARGE($I$5:$I$49,10)),"")
B64: TOP-DOWN BENCHMARK IMPUTATION (DIAGNOSE)
B65: Process-level benchmarks are not published for UK banking. Bank-level cost:income is. This block takes the only benchmark that exists and imputes what the named processes would collectively have to become to reach it. An imputed target is NOT evidence that anyone achieves it — it is the size of the problem, allocated.
B66: Cost:income ratio — as modelled | H66: =-'7. P&L'!$C$16/'7. P&L'!$C$6
B67: Cost:income ratio — target | H67: ='Inputs'!$F$199 | J67: Inputs section M. OakNorth ~26%, Allica ~50%.
B68: Total operating costs | H68: =-'7. P&L'!$C$16
B69: Operating costs at target cost:income | H69: ='7. P&L'!$C$6*'3b. Process Index'!$H$67
B70: Cost reduction required | H70: ='3b. Process Index'!$H$68-'3b. Process Index'!$H$69
B71: Cost base with a named process owner | H71: ='4. Running Costs'!$C$25+'4. Running Costs'!$C$24+'3. HR & Activity'!$H$97 | J71: Activity-driven payroll + RM cost + named head-office processes. Everything else has no process to improve.
B72: …as a share of total operating costs | H72: ='3b. Process Index'!$H$71/'3b. Process Index'!$H$68 | J72: The model's own assessment of its causal completeness. It rises as the register fills.
B73: Implied uniform improvement across process-owned cost | H73: =IF('3b. Process Index'!$H$70<=0,"no reduction required at this target",'3b. Process Index'!$H$70/'3b. Process Index'!$H$71) | J73: What every named process would have to give up, on average, to reach the target from the process-owned cost base alone. Above 100% means the target is unreachable without changing costs that no process currently owns.
B74: Gap to best in class already named bottom-up | H74: ='3. HR & Activity'!$T$101+'3. HR & Activity'!$T$97 | J74: Fills in as benchmark cells are populated. The distance between this and the required reduction is the part of the target nobody has yet explained.
B75: …required reduction not yet explained by a named benchmark gap | H75: =MAX(0,'3b. Process Index'!$H$70-'3b. Process Index'!$H$74)

Sheet 4. Running Costs
B1: STEP 2 (CONT.) — TOTAL RUNNING COSTS OF THE OPERATING UNIT
B3: Unit HR cost (from HR & Activity sheet) | C3: ='3. HR & Activity'!$H$41
B4: Premises & facilities | C4: ='3. HR & Activity'!$D$41*'Inputs'!$F$125 | D4: CP1 · all WP | E4: FTEs × cost per FTE
B5: Equipment & fit-out depreciation | C5: ='3. HR & Activity'!$D$41*'Inputs'!$F$126 | D5: E1
B6: Other direct running costs | C6: ='4. Running Costs'!$C$3*'Inputs'!$F$127 | D6: E1 | E6: Travel, training, sundry — % of HR
B7: Unit-level platform & processing | C7: ='Inputs'!$F$182*'Inputs'!$F$128*('1. Customers'!$C$4/'Inputs'!$F$182)^'Inputs'!$F$181 | D7: S2 | E7: Per-customer core banking & payments processing
B8: Fraud & payment losses (incl. APP reimbursement) | C8: ='Inputs'!$F$142*'1. Customers'!$C$12 | D8: E1 | E8: Driver: current accounts — the payment-carrying product
B9: FSCS deposit-protection levy | C9: =('1. Customers'!$E$12+'1. Customers'!$E$13+'1. Customers'!$E$14)*'Inputs'!$F$144*'Inputs'!$F$143 | D9: CA-WP | E9: Driver: FSCS-protected deposit balances
B10: TOTAL DIRECT RUNNING COSTS | C10: ='4. Running Costs'!$C$3+'4. Running Costs'!$C$4+'4. Running Costs'!$C$5+'4. Running Costs'!$C$6+'4. Running Costs'!$C$7+'4. Running Costs'!$C$8+'4. Running Costs'!$C$9 | D10: SV-WP
B12: SHARE OF HEAD-OFFICE RUNNING COSTS
B13: Technology & central operations | C13: ='Inputs'!$F$182*'Inputs'!$F$129*('1. Customers'!$C$4/'Inputs'!$F$182)^'Inputs'!$F$181+'Inputs'!$F$185 | E13: Per-customer rate + fixed component (Inputs section N)
B14: Risk, compliance, financial crime & audit | C14: ='Inputs'!$F$182*'Inputs'!$F$130*('1. Customers'!$C$4/'Inputs'!$F$182)^'Inputs'!$F$181+'Inputs'!$F$186 | E14: Per-customer rate + fixed component (Inputs section N)
B15: Finance, HR, exec, brand & residual marketing | C15: ='Inputs'!$F$182*'Inputs'!$F$131*('1. Customers'!$C$4/'Inputs'!$F$182)^'Inputs'!$F$181+'Inputs'!$F$187 | E15: Per-customer rate + fixed component (Inputs section N)
B16: Churn replacement — acquisition marketing (driver: new customers won) | C16: ='1. Customers'!$C$8*'Inputs'!$F$136 | E16: Demand generation to replace churned customers; scales with the churn input
B17: TOTAL HEAD-OFFICE ALLOCATION | C17: ='4. Running Costs'!$C$13+'4. Running Costs'!$C$14+'4. Running Costs'!$C$15+'4. Running Costs'!$C$16
B19: Change-the-bank / transformation (portfolio hurdle — no product driver) | C19: ='Inputs'!$F$182*'Inputs'!$F$145*('1. Customers'!$C$4/'Inputs'!$F$182)^'Inputs'!$F$181 | E19: Regulatory change + tech transformation; held unallocated like joint costs
B20: TOTAL OPERATING COSTS (unit + HO share + change) | C20: ='4. Running Costs'!$C$10+'4. Running Costs'!$C$17+'4. Running Costs'!$C$19
B21: Operating cost per customer | C21: ='4. Running Costs'!$C$20/'1. Customers'!$C$4
B23: COST ATTRIBUTION MEMO (ABC to the causality limit — see Unit Economics tab)
B24: RM cost (attributed to lending products as acquisition cost) | C24: ='3. HR & Activity'!$H$37
B25: Activity-driven servicing cost (analyst + service payroll) | C25: ='3. HR & Activity'!$H$38+'3. HR & Activity'!$H$39
B26: Supervision & workplace pool (managers, premises, depreciation, other) | C26: ='3. HR & Activity'!$H$40+'4. Running Costs'!$C$4+'4. Running Costs'!$C$5+'4. Running Costs'!$C$6 | E26: Driver: staff time — follows each product's share of servicing + RM cost
B27: Head-office tech attributed to named processes (tab 3 register) | C27: ='3. HR & Activity'!$H$98
B28: Head-office risk attributed to named processes (tab 3 register) | C28: ='3. HR & Activity'!$H$99
B29: Head-office corporate attributed to named processes (tab 3 register) | C29: ='3. HR & Activity'!$H$100
B30: Churn-replacement acquisition marketing attributed by driver (new customers won) | C30: ='4. Running Costs'!$C$16
B31: UNALLOCATED JOINT COSTS (brand, exec, finance, platform build, pool remainders) | C31: ='4. Running Costs'!$C$17-'3. HR & Activity'!$H$97-'4. Running Costs'!$C$30 | E31: Shrinks pound for pound as processes are named on the tab 3 register — costs are carved OUT of the pools, never added on top, so the total never moves. No causal driver exists for what remains; held as a portfolio hurdle, not forced into products.
B33: MEMO — cost base with a named process owner | C33: ='4. Running Costs'!$C$25+'4. Running Costs'!$C$24+'3. HR & Activity'!$H$97+'4. Running Costs'!$C$30 | E33: Activity-driven payroll + RM cost + named head-office processes. Everything else has no process to improve.
B34: …as a share of total operating costs | C34: ='4. Running Costs'!$C$33/'4. Running Costs'!$C$20 | E34: The model's own assessment of its causal completeness. It rises as the head-office register fills.

Sheet 5. Risk & Capital
B1: STEP 3 — INVESTMENT COSTS: EXPECTED LOSSES, CAPITAL & REQUIRED RETURN
B3: EXPECTED CREDIT LOSSES
B4: Lending product | C4: Total balances (£) | D4: Gross PD | E4: Effective PD (after RM stewardship) | F4: LGD | G4: Expected loss (£/yr) | H4: EL per unit (£)
B5: Business overdrafts | C5: ='1. Customers'!$E$15 | D5: ='Inputs'!$F$77 | E5: =D5*(1-'Inputs'!$F$167*'Inputs'!$F$166) | F5: ='Inputs'!$F$78 | G5: =C5*E5*F5 | H5: =G5/'1. Customers'!$C$15
B6: Term loans & comm. mortgages | C6: ='1. Customers'!$E$16 | D6: ='Inputs'!$F$79 | E6: =D6*(1-'Inputs'!$F$167*'Inputs'!$F$166) | F6: ='Inputs'!$F$80 | G6: =C6*E6*F6 | H6: =G6/'1. Customers'!$C$16
B7: Asset finance | C7: ='1. Customers'!$E$17 | D7: ='Inputs'!$F$81 | E7: =D7*(1-'Inputs'!$F$167*'Inputs'!$F$166) | F7: ='Inputs'!$F$82 | G7: =C7*E7*F7 | H7: =G7/'1. Customers'!$C$17
B8: Invoice finance | C8: ='1. Customers'!$E$18 | D8: ='Inputs'!$F$83 | E8: =D8*(1-'Inputs'!$F$167*'Inputs'!$F$166) | F8: ='Inputs'!$F$84 | G8: =C8*E8*F8 | H8: =G8/'1. Customers'!$C$18
B9: Business credit cards | C9: ='1. Customers'!$E$19 | D9: ='Inputs'!$F$85 | E9: =D9 | F9: ='Inputs'!$F$86 | G9: =C9*E9*F9 | H9: =G9/'1. Customers'!$C$19
B10: TOTAL EXPECTED LOSSES | G10: =SUM(G5:G9)
B11: Effective PD = gross PD × (1 − stewardship PD reduction × RM-covered share of balances). Cards are unmanaged, so uncovered.
B13: CAPITAL & REQUIRED RETURN
B14: Credit risk-weighted assets | C14: ='1. Customers'!$E$15*'Inputs'!$F$87+'1. Customers'!$E$16*'Inputs'!$F$88+'1. Customers'!$E$17*'Inputs'!$F$89+'1. Customers'!$E$18*'Inputs'!$F$90+'1. Customers'!$E$19*'Inputs'!$F$91 | I14: Balances × risk weights
B15: Operational risk-weighted assets | C15: ='2. Revenues'!$M$14*'Inputs'!$F$92 | I15: Basic-indicator proxy: gross income × 1.875
B16: TOTAL RWAs | C16: ='5. Risk & Capital'!$C$14+'5. Risk & Capital'!$C$15
B17: Equity allocated to the operating unit | C17: ='5. Risk & Capital'!$C$16*'Inputs'!$F$93 | I17: RWAs × capital ratio
B18: Equity investment benefit (equity earns Bank Rate) | C18: ='5. Risk & Capital'!$C$17*'Inputs'!$F$8 | I18: Added to income in the P&L — equity funds assets so it earns the transfer price
B19: Required return on equity (pre-tax equivalent shown post-tax in P&L) | C19: ='5. Risk & Capital'!$C$17*'Inputs'!$F$94 | I19: Equity × cost of equity — the Simanis 'second-level investment cost'

Sheet 6. Unit Economics
B1: STEPS 4 & 5 — WHOLE-COST UNIT ECONOMICS BY PRODUCT
B2: Per account / facility / user per year. Whole cost = expected loss + servicing + RM + allocated overhead; economic profit is after a charge for shareholder capital.
C4: Current accounts | D4: Instant savings | E4: Notice & fixed deposits | F4: Overdrafts | G4: Term loans | H4: Asset finance | I4: Invoice finance | J4: Credit cards | K4: Payments & FX | L4: TOTAL / blended
B5: (product key) | C5: bca | D5: sav | E5: dep | F5: od | G5: loan | H5: af | I5: inv | J5: card | K5: fx
B6: Units (accounts / facilities / users) | C6: ='1. Customers'!$C$12 | D6: ='1. Customers'!$C$13 | E6: ='1. Customers'!$C$14 | F6: ='1. Customers'!$C$15 | G6: ='1. Customers'!$C$16 | H6: ='1. Customers'!$C$17 | I6: ='1. Customers'!$C$18 | J6: ='1. Customers'!$C$19 | K6: ='1. Customers'!$C$20 | L6: =SUM(C6:K6)
B7: Average balance per unit | C7: ='1. Customers'!$D$12 | D7: ='1. Customers'!$D$13 | E7: ='1. Customers'!$D$14 | F7: ='1. Customers'!$D$15 | G7: ='1. Customers'!$D$16 | H7: ='1. Customers'!$D$17 | I7: ='1. Customers'!$D$18 | J7: ='1. Customers'!$D$19 | K7: ='1. Customers'!$D$20
B8: Revenue per unit | C8: ='2. Revenues'!$J$5 | D8: ='2. Revenues'!$J$6 | E8: ='2. Revenues'!$J$7 | F8: ='2. Revenues'!$J$8 | G8: ='2. Revenues'!$J$9 | H8: ='2. Revenues'!$J$10 | I8: ='2. Revenues'!$J$11 | J8: ='2. Revenues'!$J$12 | K8: ='2. Revenues'!$J$13 | L8: ='2. Revenues'!$M$14/L6
B9: Expected credit loss per unit | C9: =0 | D9: =0 | E9: =0 | F9: ='5. Risk & Capital'!$G$5/'1. Customers'!$C$15 | G9: ='5. Risk & Capital'!$G$6/'1. Customers'!$C$16 | H9: ='5. Risk & Capital'!$G$7/'1. Customers'!$C$17 | I9: ='5. Risk & Capital'!$G$8/'1. Customers'!$C$18 | J9: ='5. Risk & Capital'!$G$9/'1. Customers'!$C$19 | K9: =0 | L9: ='5. Risk & Capital'!$G$10/L6
B10: Servicing cost per unit (activity-driven, tab 3) | C10: =SUMIF('3. HR & Activity'!$C$11:$C$33,C5,'3. HR & Activity'!$H$11:$H$33)/'1. Customers'!$C$12 | D10: =SUMIF('3. HR & Activity'!$C$11:$C$33,D5,'3. HR & Activity'!$H$11:$H$33)/'1. Customers'!$C$13 | E10: =SUMIF('3. HR & Activity'!$C$11:$C$33,E5,'3. HR & Activity'!$H$11:$H$33)/'1. Customers'!$C$14 | F10: =SUMIF('3. HR & Activity'!$C$11:$C$33,F5,'3. HR & Activity'!$H$11:$H$33)/'1. Customers'!$C$15 | G10: =SUMIF('3. HR & Activity'!$C$11:$C$33,G5,'3. HR & Activity'!$H$11:$H$33)/'1. Customers'!$C$16 | H10: =SUMIF('3. HR & Activity'!$C$11:$C$33,H5,'3. HR & Activity'!$H$11:$H$33)/'1. Customers'!$C$17 | I10: =SUMIF('3. HR & Activity'!$C$11:$C$33,I5,'3. HR & Activity'!$H$11:$H$33)/'1. Customers'!$C$18 | J10: =SUMIF('3. HR & Activity'!$C$11:$C$33,J5,'3. HR & Activity'!$H$11:$H$33)/'1. Customers'!$C$19 | K10: =SUMIF('3. HR & Activity'!$C$11:$C$33,K5,'3. HR & Activity'!$H$11:$H$33)/'1. Customers'!$C$20 | L10: ='4. Running Costs'!$C$25/L6
B11: RM origination (CAC) per unit (per origination, tab 3) | C11: =0 | D11: =0 | E11: =0 | F11: ='3. HR & Activity'!$G$55/'1. Customers'!$C$15 | G11: ='3. HR & Activity'!$G$52/'1. Customers'!$C$16 | H11: ='3. HR & Activity'!$G$53/'1. Customers'!$C$17 | I11: ='3. HR & Activity'!$G$54/'1. Customers'!$C$18 | J11: =0 | K11: =0 | L11: ='3. HR & Activity'!$H$46/L6
B12: RM stewardship per unit (pro-rata covered balances, tab 3) | C12: =0 | D12: =0 | E12: =0 | F12: ='3. HR & Activity'!$G$61/'1. Customers'!$C$15 | G12: ='3. HR & Activity'!$G$62/'1. Customers'!$C$16 | H12: ='3. HR & Activity'!$G$63/'1. Customers'!$C$17 | I12: ='3. HR & Activity'!$G$64/'1. Customers'!$C$18 | J12: =0 | K12: =0 | L12: ='3. HR & Activity'!$H$47/L6
B13: Supervision & workplace per unit (driver: staff time) | C13: ='4. Running Costs'!$C$26*(SUMIF('3. HR & Activity'!$C$11:$C$33,C5,'3. HR & Activity'!$H$11:$H$33))/('4. Running Costs'!$C$25+'3. HR & Activity'!$H$46+'3. HR & Activity'!$H$47)/'1. Customers'!$C$12 | D13: ='4. Running Costs'!$C$26*(SUMIF('3. HR & Activity'!$C$11:$C$33,D5,'3. HR & Activity'!$H$11:$H$33))/('4. Running Costs'!$C$25+'3. HR & Activity'!$H$46+'3. HR & Activity'!$H$47)/'1. Customers'!$C$13 | E13: ='4. Running Costs'!$C$26*(SUMIF('3. HR & Activity'!$C$11:$C$33,E5,'3. HR & Activity'!$H$11:$H$33))/('4. Running Costs'!$C$25+'3. HR & Activity'!$H$46+'3. HR & Activity'!$H$47)/'1. Customers'!$C$14 | F13: ='4. Running Costs'!$C$26*(SUMIF('3. HR & Activity'!$C$11:$C$33,F5,'3. HR & Activity'!$H$11:$H$33)+'3. HR & Activity'!$G$55+'3. HR & Activity'!$G$61)/('4. Running Costs'!$C$25+'3. HR & Activity'!$H$46+'3. HR & Activity'!$H$47)/'1. Customers'!$C$15 | G13: ='4. Running Costs'!$C$26*(SUMIF('3. HR & Activity'!$C$11:$C$33,G5,'3. HR & Activity'!$H$11:$H$33)+'3. HR & Activity'!$G$52+'3. HR & Activity'!$G$62)/('4. Running Costs'!$C$25+'3. HR & Activity'!$H$46+'3. HR & Activity'!$H$47)/'1. Customers'!$C$16 | H13: ='4. Running Costs'!$C$26*(SUMIF('3. HR & Activity'!$C$11:$C$33,H5,'3. HR & Activity'!$H$11:$H$33)+'3. HR & Activity'!$G$53+'3. HR & Activity'!$G$63)/('4. Running Costs'!$C$25+'3. HR & Activity'!$H$46+'3. HR & Activity'!$H$47)/'1. Customers'!$C$17 | I13: ='4. Running Costs'!$C$26*(SUMIF('3. HR & Activity'!$C$11:$C$33,I5,'3. HR & Activity'!$H$11:$H$33)+'3. HR & Activity'!$G$54+'3. HR & Activity'!$G$64)/('4. Running Costs'!$C$25+'3. HR & Activity'!$H$46+'3. HR & Activity'!$H$47)/'1. Customers'!$C$18 | J13: ='4. Running Costs'!$C$26*(SUMIF('3. HR & Activity'!$C$11:$C$33,J5,'3. HR & Activity'!$H$11:$H$33))/('4. Running Costs'!$C$25+'3. HR & Activity'!$H$46+'3. HR & Activity'!$H$47)/'1. Customers'!$C$19 | K13: ='4. Running Costs'!$C$26*(SUMIF('3. HR & Activity'!$C$11:$C$33,K5,'3. HR & Activity'!$H$11:$H$33))/('4. Running Costs'!$C$25+'3. HR & Activity'!$H$46+'3. HR & Activity'!$H$47)/'1. Customers'!$C$20 | L13: ='4. Running Costs'!$C$26/L6
B14: Customer & account infrastructure per unit (driver-based) | C14: ='Inputs'!$F$128+'Inputs'!$F$138+'Inputs'!$F$137+'Inputs'!$F$135+'Inputs'!$F$134*'1. Customers'!$C$8/'1. Customers'!$C$12 | D14: ='Inputs'!$F$138 | E14: ='Inputs'!$F$138 | F14: ='Inputs'!$F$138+'Inputs'!$F$139 | G14: ='Inputs'!$F$138+'Inputs'!$F$139 | H14: ='Inputs'!$F$138+'Inputs'!$F$139 | I14: ='Inputs'!$F$138+'Inputs'!$F$139 | J14: ='Inputs'!$F$138+'Inputs'!$F$139 | K14: =0 | L14: =('4. Running Costs'!$C$7+'4. Running Costs'!$C$27+'4. Running Costs'!$C$28)/L6
B15: Churn-replacement acquisition per unit (driver: new customers won; gateway = current account) | C15: ='Inputs'!$F$136*'1. Customers'!$C$8/'1. Customers'!$C$12 | D15: =0 | E15: =0 | F15: =0 | G15: =0 | H15: =0 | I15: =0 | J15: =0 | K15: =0 | L15: ='4. Running Costs'!$C$16/L6
B16: Fraud & payment losses per unit (driver: current accounts) | C16: ='Inputs'!$F$142 | D16: =0 | E16: =0 | F16: =0 | G16: =0 | H16: =0 | I16: =0 | J16: =0 | K16: =0 | L16: ='4. Running Costs'!$C$8/L6
B17: FSCS levy per unit (driver: protected deposits) | C17: ='1. Customers'!$D$12*'Inputs'!$F$144*'Inputs'!$F$143 | D17: ='1. Customers'!$D$13*'Inputs'!$F$144*'Inputs'!$F$143 | E17: ='1. Customers'!$D$14*'Inputs'!$F$144*'Inputs'!$F$143 | F17: =0 | G17: =0 | H17: =0 | I17: =0 | J17: =0 | K17: =0 | L17: ='4. Running Costs'!$C$9/L6
B18: ATTRIBUTABLE COST PER UNIT (EL + servicing + RM orig + RM steward + supervision + infrastructure + churn replacement + fraud + levies) | C18: =C9+C10+C11+C12+C13+C14+C15+C16+C17 | D18: =D9+D10+D11+D12+D13+D14+D15+D16+D17 | E18: =E9+E10+E11+E12+E13+E14+E15+E16+E17 | F18: =F9+F10+F11+F12+F13+F14+F15+F16+F17 | G18: =G9+G10+G11+G12+G13+G14+G15+G16+G17 | H18: =H9+H10+H11+H12+H13+H14+H15+H16+H17 | I18: =I9+I10+I11+I12+I13+I14+I15+I16+I17 | J18: =J9+J10+J11+J12+J13+J14+J15+J16+J17 | ... L18: =L9+L10+L11+L12+L13+L14+L15+L16+L17
B19: CONTRIBUTION PER UNIT (revenue − attributable cost) | C19: =C8-C18 | D19: =D8-D18 | E19: =E8-E18 | F19: =F8-F18 | G19: =G8-G18 | H19: =H8-H18 | I19: =I8-I18 | J19: =J8-J18 | ... L19: =L8-L18
B20: Allocated equity per unit (credit + op-risk RWA × capital ratio) | C20: ='Inputs'!$F$92*C8*'Inputs'!$F$93 | D20: ='Inputs'!$F$92*D8*'Inputs'!$F$93 | E20: ='Inputs'!$F$92*E8*'Inputs'!$F$93 | F20: =('1. Customers'!$D$15*'Inputs'!$F$87+'Inputs'!$F$92*F8)*'Inputs'!$F$93 | G20: =('1. Customers'!$D$16*'Inputs'!$F$88+'Inputs'!$F$92*G8)*'Inputs'!$F$93 | H20: =('1. Customers'!$D$17*'Inputs'!$F$89+'Inputs'!$F$92*H8)*'Inputs'!$F$93 | I20: =('1. Customers'!$D$18*'Inputs'!$F$90+'Inputs'!$F$92*I8)*'Inputs'!$F$93 | J20: =('1. Customers'!$D$19*'Inputs'!$F$91+'Inputs'!$F$92*J8)*'Inputs'!$F$93 | K20: ='Inputs'!$F$92*K8*'Inputs'!$F$93
B21: Net capital charge per unit (equity × (CoE − Bank Rate)) | C21: =C20*('Inputs'!$F$94-'Inputs'!$F$8) | D21: =D20*('Inputs'!$F$94-'Inputs'!$F$8) | E21: =E20*('Inputs'!$F$94-'Inputs'!$F$8) | F21: =F20*('Inputs'!$F$94-'Inputs'!$F$8) | G21: =G20*('Inputs'!$F$94-'Inputs'!$F$8) | H21: =H20*('Inputs'!$F$94-'Inputs'!$F$8) | I21: =I20*('Inputs'!$F$94-'Inputs'!$F$8) | J21: =J20*('Inputs'!$F$94-'Inputs'!$F$8) | K21: =K20*('Inputs'!$F$94-'Inputs'!$F$8)
B22: ECONOMIC CONTRIBUTION PER UNIT (pre-tax, before joint costs) | C22: =C19-C21 | D22: =D19-D21 | E22: =E19-E21 | F22: =F19-F21 | G22: =G19-G21 | H22: =H19-H21 | I22: =I19-I21 | J22: =J19-J21 | K22: =K19-K21
B23: Economic contribution margin (% of revenue) | C23: =IF(C8=0,0,C22/C8) | D23: =IF(D8=0,0,D22/D8) | E23: =IF(E8=0,0,E22/E8) | F23: =IF(F8=0,0,F22/F8) | G23: =IF(G8=0,0,G22/G8) | H23: =IF(H8=0,0,H22/H8) | I23: =IF(I8=0,0,I22/I8) | J23: =IF(J8=0,0,J22/J8) | K23: =IF(K8=0,0,K22/K8)
B24: Total contribution (£/yr) | C24: =C19*C6 | D24: =D19*D6 | E24: =E19*E6 | F24: =F19*F6 | G24: =G19*G6 | H24: =H19*H6 | I24: =I19*I6 | J24: =J19*J6 | K24: =K19*K6 | L24: =SUM(C24:K24)
B25: Total economic contribution (£/yr) | C25: =C22*C6 | D25: =D22*D6 | E25: =E22*E6 | F25: =F22*F6 | G25: =G22*G6 | H25: =H22*H6 | I25: =I22*I6 | J25: =J22*J6 | K25: =K22*K6 | L25: =SUM(C25:K25)
B27: BRIDGE TO THE UNIT P&L
B28: Total contribution across products | C28: =L24
B29: Less: RM defence (tested retention spend, held at centre level) | C29: =-'3. HR & Activity'!$H$48
B30: Less: unallocated joint costs (no causal driver — brand, exec, finance, platform build) | C30: =-'4. Running Costs'!$C$31
B31: Less: change-the-bank / transformation (portfolio hurdle — no product driver) | C31: =-'4. Running Costs'!$C$19
B32: Operating profit before capital charges | C32: =C28+C29+C30+C31
B33: Check vs P&L (income excl. equity benefit − EL − opex) — should be zero | C33: =C32-('2. Revenues'!$M$14-'5. Risk & Capital'!$G$10-'4. Running Costs'!$C$20) | D33: ✓ ties out
B34: Memo — value of preventing ONE customer churning (contribution annuity over remaining life + avoided replacement: acquisition + onboarding + KYC) | C34: =C28/'1. Customers'!$C$4*'Inputs'!$F$169+'Inputs'!$F$136+'Inputs'!$F$105*'3. HR & Activity'!$C$7+'Inputs'!$F$134 | D34: £ per customer saved — the retention business case runs on this
B35: Memo — RM system payback: defence value (defended customers × value of one prevented churn) | C35: ='1. Customers'!$C$7*(C28/'1. Customers'!$C$4*'Inputs'!$F$169+'Inputs'!$F$136+'Inputs'!$F$105*'3. HR & Activity'!$C$7+'Inputs'!$F$134) | D35: vs defence cost: | E35: ='3. HR & Activity'!$H$48
B36: Memo — stewardship payback: expected losses avoided (tab 3) vs stewardship cost | C36: ='3. HR & Activity'!$G$65 | D36: vs stewardship cost: | E36: ='3. HR & Activity'!$H$47
B38: MEMO — FULL ABSORPTION PER SOURCE METHODOLOGY (joint costs spread per unit, as the IFC doc divides head-office costs)
B39: Joint cost absorbed per unit (flat per-unit spread) | C39: ='4. Running Costs'!$C$31/L6 | D39: ='4. Running Costs'!$C$31/L6 | E39: ='4. Running Costs'!$C$31/L6 | F39: ='4. Running Costs'!$C$31/L6 | G39: ='4. Running Costs'!$C$31/L6 | H39: ='4. Running Costs'!$C$31/L6 | I39: ='4. Running Costs'!$C$31/L6 | J39: ='4. Running Costs'!$C$31/L6 | K39: ='4. Running Costs'!$C$31/L6 | L39: ='4. Running Costs'!$C$31/L6
B40: Fully-absorbed profit per unit (contribution − joint absorption) | C40: =C19-C39 | D40: =D19-D39 | E40: =E19-E39 | F40: =F19-F39 | G40: =G19-G39 | H40: =H19-H39 | I40: =I19-I39 | J40: =J19-J39 | K40: =K19-K39
B42: Cost treatment follows the source methodology's own hybrid: activity drivers wherever a causal link to customers or transactions exists ('whenever possible' — Simanis IFC Technical Doc Part II), head-office residuals without a driver held as an unallocated share rather than forced into products. Product decisions should run on CONTRIBUTION (it changes when the decision changes); the full-absorption memo shows required pricing coverage.

Sheet 7. P&L
B1: STEP 5 — WHOLE-COST P&L: ONE OPERATING UNIT AT STEADY STATE
B3: Net interest income (vs funds transfer price) | C3: ='2. Revenues'!$K$14
B4: Fee & commission income | C4: ='2. Revenues'!$L$14
B5: Equity investment benefit | C5: ='5. Risk & Capital'!$C$18 | E5: Allocated equity earning Bank Rate
B6: TOTAL OPERATING INCOME | C6: ='7. P&L'!$C$3+'7. P&L'!$C$4+'7. P&L'!$C$5
B7: Expected credit losses | C7: =-'5. Risk & Capital'!$G$10
B8: NET OPERATING INCOME | C8: ='7. P&L'!$C$6+'7. P&L'!$C$7
B9: Staff costs (unit) | C9: =-'4. Running Costs'!$C$3
B10: Premises & depreciation | C10: =-'4. Running Costs'!$C$4-'4. Running Costs'!$C$5
B11: Other direct costs & unit platform | C11: =-'4. Running Costs'!$C$6-'4. Running Costs'!$C$7
B12: Fraud & payment losses (incl. APP reimbursement) | C12: =-'4. Running Costs'!$C$8
B13: FSCS deposit-protection levy | C13: =-'4. Running Costs'!$C$9
B14: Share of head-office costs | C14: =-'4. Running Costs'!$C$17
B15: Change-the-bank / transformation | C15: =-'4. Running Costs'!$C$19 | E15: Portfolio hurdle — not attributed to products
B16: TOTAL OPERATING COSTS | C16: ='7. P&L'!$C$9+'7. P&L'!$C$10+'7. P&L'!$C$11+'7. P&L'!$C$12+'7. P&L'!$C$13+'7. P&L'!$C$14+'7. P&L'!$C$15
B17: memo: attributed to products by driver (ABC — tab 6) | C17: ='7. P&L'!$C$16+'4. Running Costs'!$C$31+'3. HR & Activity'!$H$48 | E17: Servicing, RM origination & stewardship, supervision & workplace, account infrastructure
B18: memo: RM defence — tested retention spend at centre level | C18: =-'3. HR & Activity'!$H$48 | E18: Pays back through reduced churn (see bridge memo, tab 6)
B19: memo: unallocated joint costs (portfolio hurdle) | C19: =-'4. Running Costs'!$C$31 | E19: Brand, exec, finance, platform build — no causal driver; total contribution must clear these
B20: PROFIT BEFORE TAX | C20: ='7. P&L'!$C$8+'7. P&L'!$C$16
B21: Tax (corporation tax + bank surcharge) | C21: =-'7. P&L'!$C$20*'Inputs'!$F$95
B22: PROFIT AFTER TAX | C22: ='7. P&L'!$C$20+'7. P&L'!$C$21
B23: Required return on allocated equity (post-tax) | C23: =-'5. Risk & Capital'!$C$19 | E23: Simanis second-level investment cost: what shareholders must earn
B24: ECONOMIC PROFIT (value created above cost of equity) | C24: ='7. P&L'!$C$22+'7. P&L'!$C$23
B26: KEY RATIOS & BENCHMARKS
B27: Customers | C27: ='1. Customers'!$C$4
B28: Revenue per customer | C28: ='7. P&L'!$C$6/'1. Customers'!$C$4
B29: Operating cost per customer | C29: =-'7. P&L'!$C$16/'1. Customers'!$C$4
B30: Cost:income ratio | C30: =-'7. P&L'!$C$16/'7. P&L'!$C$6 | E30: Specialist SME banks: OakNorth ~26%, Allica ~50% while scaling; majors' business banking 50%+
B31: Cost of risk (EL / lending balances) | C31: =-'7. P&L'!$C$7/'1. Customers'!$E$22 | E31: BoE: SME impairments are the biggest drag on SME lending returns
B32: NII / lending balances (indicative NIM) | C32: ='7. P&L'!$C$3/'1. Customers'!$E$22
B33: Return on allocated equity (RoE) | C33: ='7. P&L'!$C$22/'5. Risk & Capital'!$C$17 | E33: Strong SME specialists earn 15–25%; sector cost of equity ~10–14%
B34: Loan-to-deposit ratio | C34: ='1. Customers'!$E$22/'1. Customers'!$E$21
B36: COST DRIVERS (each line as % of whole costs — Simanis cost-driver analysis)
B37: Expected credit losses | C37: =-'7. P&L'!$C$7 | D37: =-'7. P&L'!$C$7/(-'7. P&L'!$C$7-'7. P&L'!$C$16)
B38: Staff costs (unit) | C38: =-'7. P&L'!$C$9 | D38: =-'7. P&L'!$C$9/(-'7. P&L'!$C$7-'7. P&L'!$C$16)
B39: Premises & depreciation | C39: =-'7. P&L'!$C$10 | D39: =-'7. P&L'!$C$10/(-'7. P&L'!$C$7-'7. P&L'!$C$16)
B40: Other direct & unit platform | C40: =-'7. P&L'!$C$11 | D40: =-'7. P&L'!$C$11/(-'7. P&L'!$C$7-'7. P&L'!$C$16)
B41: Fraud & payment losses | C41: =-'7. P&L'!$C$12 | D41: =-'7. P&L'!$C$12/(-'7. P&L'!$C$7-'7. P&L'!$C$16)
B42: FSCS levy | C42: =-'7. P&L'!$C$13 | D42: =-'7. P&L'!$C$13/(-'7. P&L'!$C$7-'7. P&L'!$C$16)
B43: Head-office allocation | C43: =-'7. P&L'!$C$14 | D43: =-'7. P&L'!$C$14/(-'7. P&L'!$C$7-'7. P&L'!$C$16)
B44: Change-the-bank / transformation | C44: =-'7. P&L'!$C$15 | D44: =-'7. P&L'!$C$15/(-'7. P&L'!$C$7-'7. P&L'!$C$16)
B45: WHOLE COSTS (running + risk) | C45: =(-'7. P&L'!$C$7-'7. P&L'!$C$16) | D45: 1
B47: The largest percentages are the leverage points: trace them back to transaction intensity (I) or customer load (L) on the HR & Activity sheet and innovate there first.

Sheet 8. Org Structure
B1: ORG STRUCTURE — WHOLE BANK AT SCALE
B2: Front-line FTEs come straight from the activity drivers (tab 3) × number of centres; head-office FTEs are backed out of the per-customer head-office allocations (tab 4).
B4: BANK AT SCALE
B5: Regional business centres | C5: ='Inputs'!$F$172
B6: Customers | C6: ='Inputs'!$F$172*'1. Customers'!$C$4
B7: Lending balances | C7: ='Inputs'!$F$172*'1. Customers'!$E$22
B8: Customer deposits | C8: ='Inputs'!$F$172*'1. Customers'!$E$21
B9: Total operating income | C9: ='Inputs'!$F$172*'7. P&L'!$C$6
B10: Total operating costs | C10: ='Inputs'!$F$172*-'7. P&L'!$C$16
B12: FRONT LINE — ROLE TOTALS (derived from activity drivers; organised into segment pods below)
B13: Role | C13: FTE per centre | D13: FTE at scale | E13: Headcount (rounded) | H13: Basis
B14: Business centre managers | C14: ='3. HR & Activity'!$D$40 | D14: =C14*'Inputs'!$F$172 | E14: =ROUND(D14,0) | H14: Span of control: 8 staff per manager
B15: Relationship managers | C15: ='3. HR & Activity'!$D$37 | D15: =C15*'Inputs'!$F$172 | E15: =ROUND(D15,0) | H15: Customer load: 120 RM-managed customers per RM
B16: Credit analysts / underwriters | C16: ='3. HR & Activity'!$D$38 | D16: =C16*'Inputs'!$F$172 | E16: =ROUND(D16,0) | H16: Underwriting, reviews, monitoring & collections hours (tab 3)
B17: Service & operations staff | C17: ='3. HR & Activity'!$D$39 | D17: =C17*'Inputs'!$F$172 | E17: =ROUND(D17,0) | H17: Onboarding & account servicing hours (tab 3)
B18: TOTAL FRONT LINE | D18: =SUM(D14:D17) | E18: =SUM(E14:E17)
B20: SEGMENT PODS — THE OPERATIONAL LMUs (bounded by customer segment, not geography)
B21: National customer base | C21: ='8. Org Structure'!$C$6
B22: Segment: relationship-managed SMEs (larger / complex) | C22: ='8. Org Structure'!$C$21*'Inputs'!$F$24 | H22: The segment boundary is customer size & complexity — pct_rm input
B23: Segment: digitally-served small businesses | C23: ='8. Org Structure'!$C$21-'8. Org Structure'!$C$22
B25: RELATIONSHIP POD (LMU for the RM-managed segment)
B26: Pod capacity (RMs per pod × customers per RM) | C26: ='Inputs'!$F$26*'Inputs'!$F$25 | H26: 6 RMs × 120 customers = 720 SMEs per pod
B27: Relationship pods at scale | C27: ='8. Org Structure'!$C$22/'8. Org Structure'!$C$26 | H27: Replicating unit: pod lead + RMs + analysts; carries ~60% of lending balances
B28: Credit analysts per pod (national analysts ÷ pods) | C28: ='3. HR & Activity'!$D$38*'Inputs'!$F$172/'8. Org Structure'!$C$27 | H28: Analysts sit with the relationship pods; digitally-held credit is underwritten remotely by the same pods
B30: DIGITAL SERVICE POD (LMU for the small-business segment)
B31: Digital service pods at scale (service FTE ÷ pod size) | C31: ='3. HR & Activity'!$D$39*'Inputs'!$F$172/'Inputs'!$F$27 | H31: Replicating unit: service & ops FTE serving the segment via app + contact centre
B32: Small businesses served per digital pod | C32: ='8. Org Structure'!$C$23/'8. Org Structure'!$C$31 | H32: Capacity bounded by service workload, not territory
B34: Both pod types replicate independently as the bank grows — the segment pod, not a regional centre, is the venture's replicating building block. Geography is only where pods are homed.
B36: HEAD OFFICE — FTEs BACKED OUT OF COST ALLOCATIONS
B37: Division | C37: Allocated cost at scale | D37: Staff share | E37: Staff cost (£) | F37: Loaded cost /FTE | G37: FTEs | H37: Note
B38: Technology & central operations | C38: ='Inputs'!$F$129*'8. Org Structure'!$C$6 | D38: ='Inputs'!$F$173 | E38: =C38*D38 | F38: ='Inputs'!$F$174 | G38: =E38/F38
B39: Risk, compliance, financial crime & audit | C39: ='Inputs'!$F$130*'8. Org Structure'!$C$6 | D39: ='Inputs'!$F$175 | E39: =C39*D39 | F39: ='Inputs'!$F$176 | G39: =E39/F39
B40: Corporate centre (finance, treasury, HR, marketing, exec) | C40: ='Inputs'!$F$131*'8. Org Structure'!$C$6 | D40: ='Inputs'!$F$177 | E40: =C40*D40 | F40: ='Inputs'!$F$178 | G40: =E40/F40
B41: TOTAL HEAD OFFICE | G41: =SUM(G38:G40)
B43: INDICATIVE SPLIT WITHIN EACH HEAD-OFFICE DIVISION (edit blue % — each block sums to 100%)
B44: Function | C44: % of division | D44: FTEs | E44: Headcount (rounded)
B45: TECHNOLOGY & CENTRAL OPERATIONS
B46: Engineering & platform development | C46: 0.4 | D46: =C46*'8. Org Structure'!$G$38 | E46: =ROUND(D46,0)
B47: IT infrastructure & security | C47: 0.18 | D47: =C47*'8. Org Structure'!$G$38 | E47: =ROUND(D47,0)
B48: Payments & banking operations | C48: 0.27 | D48: =C48*'8. Org Structure'!$G$38 | E48: =ROUND(D48,0)
B49: Onboarding, KYC refresh & complaints | C49: 0.15 | D49: =C49*'8. Org Structure'!$G$38 | E49: =ROUND(D49,0)
B50: RISK, COMPLIANCE, FINANCIAL CRIME & AUDIT
B51: Credit risk & underwriting policy | C51: 0.3 | D51: =C51*'8. Org Structure'!$G$39 | E51: =ROUND(D51,0)
B52: Compliance & conduct | C52: 0.2 | D52: =C52*'8. Org Structure'!$G$39 | E52: =ROUND(D52,0)
B53: Financial crime & fraud | C53: 0.26 | D53: =C53*'8. Org Structure'!$G$39 | E53: =ROUND(D53,0)
B54: Operational risk | C54: 0.08 | D54: =C54*'8. Org Structure'!$G$39 | E54: =ROUND(D54,0)
B55: Internal audit | C55: 0.08 | D55: =C55*'8. Org Structure'!$G$39 | E55: =ROUND(D55,0)
B56: Legal & company secretariat | C56: 0.08 | D56: =C56*'8. Org Structure'!$G$39 | E56: =ROUND(D56,0)
B57: CORPORATE CENTRE
B58: Finance & regulatory reporting | C58: 0.31 | D58: =C58*'8. Org Structure'!$G$40 | E58: =ROUND(D58,0)
B59: Treasury & ALM | C59: 0.12 | D59: =C59*'8. Org Structure'!$G$40 | E59: =ROUND(D59,0)
B60: People / HR | C60: 0.16 | D60: =C60*'8. Org Structure'!$G$40 | E60: =ROUND(D60,0)
B61: Marketing & brand (residual — acquisition carved out to cac_new) | C61: 0.12 | D61: =C61*'8. Org Structure'!$G$40 | E61: =ROUND(D61,0)
B62: Executive & strategy | C62: 0.13 | D62: =C62*'8. Org Structure'!$G$40 | E62: =ROUND(D62,0)
B63: Facilities & procurement | C63: 0.09 | D63: =C63*'8. Org Structure'!$G$40 | E63: =ROUND(D63,0)
B64: Data & MI | C64: 0.07 | D64: =C64*'8. Org Structure'!$G$40 | E64: =ROUND(D64,0)
B66: WHOLE-BANK TOTALS
B67: Total bank FTEs (front line + head office) | C67: ='8. Org Structure'!$D$18+'8. Org Structure'!$G$41
B68: Customers per FTE | C68: ='8. Org Structure'!$C$6/'8. Org Structure'!$C$67
B69: Operating income per FTE | C69: ='8. Org Structure'!$C$9/'8. Org Structure'!$C$67 | H69: UK banks typically £250–400k income per FTE
B70: Implied total staff cost | C70: ='Inputs'!$F$172*'3. HR & Activity'!$H$41+'8. Org Structure'!$E$38+'8. Org Structure'!$E$39+'8. Org Structure'!$E$40
B71: Staff cost as % of total operating costs | C71: ='8. Org Structure'!$C$70/'8. Org Structure'!$C$10 | H71: Banks typically ~55–65% of opex is people
B73: Front-line FTEs are fractional per centre (e.g. 3.75 RMs); in practice centres share specialists or round up — the 'Headcount (rounded)' column shows the practical org.

Sheet 9. Flow Register
B1: FLOW REGISTER — PORTFOLIO OF 4-D PRODUCTS ON A SHARED PLATFORM
B2: One row per flow. Each product line is a full 4-D product whose working product is DERIVED from its CTM state change (uk_sme_bank_ctm.html); the shared platform serves every product. Reconciles the map's role pills to the ARM (tab 3) and each flow's processes to BIAN.
B4: Flow | C4: Product | D4: Type | E4: Category | F4: Name | G4: State change driven (from CTM) | H4: Direction | I4: Medium | J4: Direct producer | K4: Admin support | L4: Managerial support | M4: BIAN service domains
B5: CP1 | C5: Shared platform | D5: CP | E5: Comms | F5: Marketing & brand | G5: — | H5: HQ->cust | I5: digital | J5: Marketing | K5: Marketing admin | L5: Head of marketing | M5: Marketing Campaign · Brand Management
B6: CA-WP | C6: Current account | D6: WP | E6: Core | F6: Hold & use day-to-day money | G6: Business money mixed & ad hoc -> held safe, usable on demand | H6: HQ->cust | I6: digital | J6: Service & ops | K6: Ops admin | L6: Ops manager | M6: Current Account · Party Reference Data
B7: CA-PP1 | C7: Current account | D7: PP | E7: Money | F7: Account fees | G7: — | H7: cust->HQ | I7: digital | J7: Payments ops | K7: Finance admin | L7: Payments manager | M7: Customer Billing · Reconciliation
B8: SV-WP | C8: Savings & deposits | D8: WP | E8: Core | F8: Interest-earning safe store | G8: Surplus idle -> surplus earning | H8: HQ->cust | I8: digital | J8: Service & ops | K8: Ops admin | L8: Ops manager | M8: Savings Account · Term Deposit
B9: SV-PP1 | C9: Savings & deposits | D9: PP | E9: Money | F9: Deposits placed | G9: — | H9: cust->HQ | I9: digital | J9: Treasury | K9: Ops admin | L9: Treasurer | M9: Payment Execution · Position Keeping
B10: SV-PP2 | C10: Savings & deposits | D10: PP | E10: Money | F10: Interest paid | G10: — | H10: HQ->cust | I10: digital | J10: Treasury | K10: Finance admin | L10: Treasurer | M10: Customer Billing · Position Keeping
B11: LN-WP | C11: Lending & credit | D11: WP | E11: Core | F11: Credit facility (loans · OD · asset & invoice finance) | G11: Opportunity unfundable -> funded | H11: HQ->cust | I11: physical | J11: RM · Credit analyst | K11: Credit admin | L11: Credit risk manager | M11: Loan · Customer Credit Rating · Collateral Administration
B12: LN-PP1 | C12: Lending & credit | D12: PP | E12: Money | F12: Drawdown | G12: — | H12: HQ->cust | I12: digital | J12: Treasury | K12: Ops admin | L12: Treasurer | M12: Payment Execution · Position Keeping
B13: LN-PP2 | C13: Lending & credit | D13: PP | E13: Money | F13: Repayments & interest | G13: — | H13: cust->HQ | I13: digital | J13: Payments ops | K13: Finance admin | L13: Payments manager | M13: Payment Execution · Reconciliation
B14: CC-WP | C14: Business credit card | D14: WP | E14: Core | F14: Revolving credit line | G14: Spend blocked by cash timing -> spend enabled on credit | H14: HQ->cust | I14: digital | J14: Service & ops | K14: Ops admin | L14: Ops manager | M14: Card Authorization · Issued Device Admin
B15: CC-PP1 | C15: Business credit card | D15: PP | E15: Money | F15: Spend settled | G15: — | H15: HQ->cust | I15: digital | J15: Payments ops | K15: Payments admin | L15: Payments manager | M15: Card Clearing · Reconciliation
... B35: I3 | C35: Bank boundary | D35: Info | E35: Info-out | F35: Open Banking data out to TPPs (customer-permissioned, via E3) | G35: — | H35: HQ->TPPs | I35: digital | J35: Digital · IT | K35: — | L35: Head of Digital | M35: Financial Message Gateway
B37: PER-FLOW COSTED ACTIVITIES & DRI — activity cost per flow with [low, high] band; one accountable owner per flow
B38: Flow | C38: DRI (single accountable owner) | D38: Activity cost (£/yr) | E38: Low (£/yr) | F38: High (£/yr) | G38: Costed via
B39: CP1 | C39: Head of Marketing | D39: =SUMIF('3. HR & Activity'!$I$11:$I$33,"*CP1*",'3. HR & Activity'!$H$11:$H$33) | E39: =SUMIF('3. HR & Activity'!$I$11:$I$33,"*CP1*",'3. HR & Activity'!$J$11:$J$33) | F39: =SUMIF('3. HR & Activity'!$I$11:$I$33,"*CP1*",'3. HR & Activity'!$K$11:$K$33) | G39: Churn-replacement acquisition driver-costed (cac_new × new customers won); residual brand pool (in hq_oh) pool-costed
B40: CA-WP | C40: Head of Business Current Accounts | D40: =SUMIF('3. HR & Activity'!$I$11:$I$33,"*CA-WP*",'3. HR & Activity'!$H$11:$H$33) | E40: =SUMIF('3. HR & Activity'!$I$11:$I$33,"*CA-WP*",'3. HR & Activity'!$J$11:$J$33) | F40: =SUMIF('3. HR & Activity'!$I$11:$I$33,"*CA-WP*",'3. HR & Activity'!$K$11:$K$33) | G40: Activity rows (onboarding incl. KYC screening · account servicing) + per-account infrastructure drivers
B41: CA-PP1 | C41: Head of Business Current Accounts | D41: =SUMIF('3. HR & Activity'!$I$11:$I$33,"*CA-PP1*",'3. HR & Activity'!$H$11:$H$33) | E41: =SUMIF('3. HR & Activity'!$I$11:$I$33,"*CA-PP1*",'3. HR & Activity'!$J$11:$J$33) | F41: =SUMIF('3. HR & Activity'!$I$11:$I$33,"*CA-PP1*",'3. HR & Activity'!$K$11:$K$33) | G41: Billing inside payments infrastructure (pay_bca driver)
B42: SV-WP | C42: Head of Deposits | D42: =SUMIF('3. HR & Activity'!$I$11:$I$33,"*SV-WP*",'3. HR & Activity'!$H$11:$H$33) | E42: =SUMIF('3. HR & Activity'!$I$11:$I$33,"*SV-WP*",'3. HR & Activity'!$J$11:$J$33) | F42: =SUMIF('3. HR & Activity'!$I$11:$I$33,"*SV-WP*",'3. HR & Activity'!$K$11:$K$33) | G42: Activity rows (savings & deposit servicing)
B43: SV-PP1 | C43: Treasurer | D43: =SUMIF('3. HR & Activity'!$I$11:$I$33,"*SV-PP1*",'3. HR & Activity'!$H$11:$H$33) | E43: =SUMIF('3. HR & Activity'!$I$11:$I$33,"*SV-PP1*",'3. HR & Activity'!$J$11:$J$33) | F43: =SUMIF('3. HR & Activity'!$I$11:$I$33,"*SV-PP1*",'3. HR & Activity'!$K$11:$K$33) | G43: Treasury/settlement — infrastructure drivers, no front-line activity rows
B44: SV-PP2 | C44: Treasurer | D44: =SUMIF('3. HR & Activity'!$I$11:$I$33,"*SV-PP2*",'3. HR & Activity'!$H$11:$H$33) | E44: =SUMIF('3. HR & Activity'!$I$11:$I$33,"*SV-PP2*",'3. HR & Activity'!$J$11:$J$33) | F44: =SUMIF('3. HR & Activity'!$I$11:$I$33,"*SV-PP2*",'3. HR & Activity'!$K$11:$K$33) | G44: Interest posting — automated; core banking driver (core_acct)
B45: LN-WP | C45: Credit Director | D45: =SUMIF('3. HR & Activity'!$I$11:$I$33,"*LN-WP*",'3. HR & Activity'!$H$11:$H$33) | E45: =SUMIF('3. HR & Activity'!$I$11:$I$33,"*LN-WP*",'3. HR & Activity'!$J$11:$J$33) | F45: =SUMIF('3. HR & Activity'!$I$11:$I$33,"*LN-WP*",'3. HR & Activity'!$K$11:$K$33) | G45: Activity rows (underwriting · reviews · IF monitoring · collections · collateral · workout) + RM origination/stewardship (tab 3 RM system)
B46: LN-PP1 | C46: Treasurer | D46: =SUMIF('3. HR & Activity'!$I$11:$I$33,"*LN-PP1*",'3. HR & Activity'!$H$11:$H$33) | E46: =SUMIF('3. HR & Activity'!$I$11:$I$33,"*LN-PP1*",'3. HR & Activity'!$J$11:$J$33) | F46: =SUMIF('3. HR & Activity'!$I$11:$I$33,"*LN-PP1*",'3. HR & Activity'!$K$11:$K$33) | G46: Drawdown execution — payments infrastructure
B47: LN-PP2 | C47: Head of Payments & FX | D47: =SUMIF('3. HR & Activity'!$I$11:$I$33,"*LN-PP2*",'3. HR & Activity'!$H$11:$H$33) | E47: =SUMIF('3. HR & Activity'!$I$11:$I$33,"*LN-PP2*",'3. HR & Activity'!$J$11:$J$33) | F47: =SUMIF('3. HR & Activity'!$I$11:$I$33,"*LN-PP2*",'3. HR & Activity'!$K$11:$K$33) | G47: Collection & application of repayments — payments infrastructure
B48: CC-WP | C48: Head of Cards | D48: =SUMIF('3. HR & Activity'!$I$11:$I$33,"*CC-WP*",'3. HR & Activity'!$H$11:$H$33) | E48: =SUMIF('3. HR & Activity'!$I$11:$I$33,"*CC-WP*",'3. HR & Activity'!$J$11:$J$33) | F48: =SUMIF('3. HR & Activity'!$I$11:$I$33,"*CC-WP*",'3. HR & Activity'!$K$11:$K$33) | G48: Activity rows (card servicing · card collections) + credit systems driver (credit_fac)
B49: CC-PP1 | C49: Head of Cards | D49: =SUMIF('3. HR & Activity'!$I$11:$I$33,"*CC-PP1*",'3. HR & Activity'!$H$11:$H$33) | E49: =SUMIF('3. HR & Activity'!$I$11:$I$33,"*CC-PP1*",'3. HR & Activity'!$J$11:$J$33) | F49: =SUMIF('3. HR & Activity'!$I$11:$I$33,"*CC-PP1*",'3. HR & Activity'!$K$11:$K$33) | G49: Scheme settlement — scheme fees inside tech pool
B50: CC-PP2 | C50: Head of Cards | D50: =SUMIF('3. HR & Activity'!$I$11:$I$33,"*CC-PP2*",'3. HR & Activity'!$H$11:$H$33) | E50: =SUMIF('3. HR & Activity'!$I$11:$I$33,"*CC-PP2*",'3. HR & Activity'!$J$11:$J$33) | F50: =SUMIF('3. HR & Activity'!$I$11:$I$33,"*CC-PP2*",'3. HR & Activity'!$K$11:$K$33) | G50: Interchange collection — scheme rails
B51: PX-WP | C51: Head of Payments & FX | D51: =SUMIF('3. HR & Activity'!$I$11:$I$33,"*PX-WP*",'3. HR & Activity'!$H$11:$H$33) | E51: =SUMIF('3. HR & Activity'!$I$11:$I$33,"*PX-WP*",'3. HR & Activity'!$J$11:$J$33) | F51: =SUMIF('3. HR & Activity'!$I$11:$I$33,"*PX-WP*",'3. HR & Activity'!$K$11:$K$33) | G51: Activity rows (payments & FX support) + payments processing driver (pay_bca)
B52: PX-PP1 | C52: Head of Payments & FX | D52: =SUMIF('3. HR & Activity'!$I$11:$I$33,"*PX-PP1*",'3. HR & Activity'!$H$11:$H$33) | E52: =SUMIF('3. HR & Activity'!$I$11:$I$33,"*PX-PP1*",'3. HR & Activity'!$J$11:$J$33) | F52: =SUMIF('3. HR & Activity'!$I$11:$I$33,"*PX-PP1*",'3. HR & Activity'!$K$11:$K$33) | G52: Payment execution — payments infrastructure + scheme fees
B53: PX-PP2 | C53: Head of Payments & FX | D53: =SUMIF('3. HR & Activity'!$I$11:$I$33,"*PX-PP2*",'3. HR & Activity'!$H$11:$H$33) | E53: =SUMIF('3. HR & Activity'!$I$11:$I$33,"*PX-PP2*",'3. HR & Activity'!$J$11:$J$33) | F53: =SUMIF('3. HR & Activity'!$I$11:$I$33,"*PX-PP2*",'3. HR & Activity'!$K$11:$K$33) | G53: Receipt processing — payments infrastructure
B54: E1 | C54: Head of Digital | D54: =SUMIF('3. HR & Activity'!$I$11:$I$33,"*E1*",'3. HR & Activity'!$H$11:$H$33) | E54: =SUMIF('3. HR & Activity'!$I$11:$I$33,"*E1*",'3. HR & Activity'!$J$11:$J$33) | F54: =SUMIF('3. HR & Activity'!$I$11:$I$33,"*E1*",'3. HR & Activity'!$K$11:$K$33) | G54: Tech per-customer driver (tech_acct) + HQ tech pool — no activity rows
B55: E2 | C55: Head of Business Current Accounts | D55: =SUMIF('3. HR & Activity'!$I$11:$I$33,"*E2*",'3. HR & Activity'!$H$11:$H$33) | E55: =SUMIF('3. HR & Activity'!$I$11:$I$33,"*E2*",'3. HR & Activity'!$J$11:$J$33) | F55: =SUMIF('3. HR & Activity'!$I$11:$I$33,"*E2*",'3. HR & Activity'!$K$11:$K$33) | G55: Card issuance & scheme costs — tech pool
B56: E3 | C56: Head of Digital | D56: =SUMIF('3. HR & Activity'!$I$11:$I$33,"*E3*",'3. HR & Activity'!$H$11:$H$33) | E56: =SUMIF('3. HR & Activity'!$I$11:$I$33,"*E3*",'3. HR & Activity'!$J$11:$J$33) | F56: =SUMIF('3. HR & Activity'!$I$11:$I$33,"*E3*",'3. HR & Activity'!$K$11:$K$33) | G56: API/gateway — HQ tech pool
B57: E4 | C57: Head of Information Security | D57: =SUMIF('3. HR & Activity'!$I$11:$I$33,"*E4*",'3. HR & Activity'!$H$11:$H$33) | E57: =SUMIF('3. HR & Activity'!$I$11:$I$33,"*E4*",'3. HR & Activity'!$J$11:$J$33) | F57: =SUMIF('3. HR & Activity'!$I$11:$I$33,"*E4*",'3. HR & Activity'!$K$11:$K$33) | G57: Authentication & entitlement — HQ tech pool; KYC screening costed inside CA-WP onboarding
B58: E5 | C58: Head of Operations | D58: =SUMIF('3. HR & Activity'!$I$11:$I$33,"*E5*",'3. HR & Activity'!$H$11:$H$33) | E58: =SUMIF('3. HR & Activity'!$I$11:$I$33,"*E5*",'3. HR & Activity'!$J$11:$J$33) | F58: =SUMIF('3. HR & Activity'!$I$11:$I$33,"*E5*",'3. HR & Activity'!$K$11:$K$33) | G58: Document store — HQ tech pool
B59: S1 | C59: Head of Customer Service | D59: =SUMIF('3. HR & Activity'!$I$11:$I$33,"*S1*",'3. HR & Activity'!$H$11:$H$33) | E59: =SUMIF('3. HR & Activity'!$I$11:$I$33,"*S1*",'3. HR & Activity'!$J$11:$J$33) | F59: =SUMIF('3. HR & Activity'!$I$11:$I$33,"*S1*",'3. HR & Activity'!$K$11:$K$33) | G59: Contact-centre share of servicing activity rows (t_bca et al.)
B60: S2 | C60: Head of Operations | D60: =SUMIF('3. HR & Activity'!$I$11:$I$33,"*S2*",'3. HR & Activity'!$H$11:$H$33) | E60: =SUMIF('3. HR & Activity'!$I$11:$I$33,"*S2*",'3. HR & Activity'!$J$11:$J$33) | F60: =SUMIF('3. HR & Activity'!$I$11:$I$33,"*S2*",'3. HR & Activity'!$K$11:$K$33) | G60: Statement generation — automated; core banking driver
B61: S3 | C61: Head of Conduct & Complaints | D61: =SUMIF('3. HR & Activity'!$I$11:$I$33,"*S3*",'3. HR & Activity'!$H$11:$H$33) | E61: =SUMIF('3. HR & Activity'!$I$11:$I$33,"*S3*",'3. HR & Activity'!$J$11:$J$33) | F61: =SUMIF('3. HR & Activity'!$I$11:$I$33,"*S3*",'3. HR & Activity'!$K$11:$K$33) | G61: Complaint handling — inside HQ risk pool; add an activity row if volumes become material
B62: S4 | C62: Head of Financial Crime | D62: =SUMIF('3. HR & Activity'!$I$11:$I$33,"*S4*",'3. HR & Activity'!$H$11:$H$33) | E62: =SUMIF('3. HR & Activity'!$I$11:$I$33,"*S4*",'3. HR & Activity'!$J$11:$J$33) | F62: =SUMIF('3. HR & Activity'!$I$11:$I$33,"*S4*",'3. HR & Activity'!$K$11:$K$33) | G62: Fraud ops — HQ risk pool + fraud loss line (P&L); reimbursement outflow shown in fidelity table
B63: PartP1 | C63: Treasurer | D63: =SUMIF('3. HR & Activity'!$I$11:$I$33,"*PartP1*",'3. HR & Activity'!$H$11:$H$33) | E63: =SUMIF('3. HR & Activity'!$I$11:$I$33,"*PartP1*",'3. HR & Activity'!$J$11:$J$33) | F63: =SUMIF('3. HR & Activity'!$I$11:$I$33,"*PartP1*",'3. HR & Activity'!$K$11:$K$33) | G63: Treasury & partner management — HQ pools
B64: PartP2 | C64: CFO | D64: =SUMIF('3. HR & Activity'!$I$11:$I$33,"*PartP2*",'3. HR & Activity'!$H$11:$H$33) | E64: =SUMIF('3. HR & Activity'!$I$11:$I$33,"*PartP2*",'3. HR & Activity'!$J$11:$J$33) | F64: =SUMIF('3. HR & Activity'!$I$11:$I$33,"*PartP2*",'3. HR & Activity'!$K$11:$K$33) | G64: Equity servicing — required return line (tab 5)
B65: PartP3 | C65: HR Director | D65: =SUMIF('3. HR & Activity'!$I$11:$I$33,"*PartP3*",'3. HR & Activity'!$H$11:$H$33) | E65: =SUMIF('3. HR & Activity'!$I$11:$I$33,"*PartP3*",'3. HR & Activity'!$J$11:$J$33) | F65: =SUMIF('3. HR & Activity'!$I$11:$I$33,"*PartP3*",'3. HR & Activity'!$K$11:$K$33) | G65: ALL front-line salary cost = the activity rows themselves; HQ salaries in HQ pools
B66: PartP4 | C66: Head of Procurement | D66: =SUMIF('3. HR & Activity'!$I$11:$I$33,"*PartP4*",'3. HR & Activity'!$H$11:$H$33) | E66: =SUMIF('3. HR & Activity'!$I$11:$I$33,"*PartP4*",'3. HR & Activity'!$J$11:$J$33) | F66: =SUMIF('3. HR & Activity'!$I$11:$I$33,"*PartP4*",'3. HR & Activity'!$K$11:$K$33) | G66: Premises · depreciation · other · tech vendor lines (tab 4)
B67: I1 | C67: Head of Regulatory Reporting | D67: =SUMIF('3. HR & Activity'!$I$11:$I$33,"*I1*",'3. HR & Activity'!$H$11:$H$33) | E67: =SUMIF('3. HR & Activity'!$I$11:$I$33,"*I1*",'3. HR & Activity'!$J$11:$J$33) | F67: =SUMIF('3. HR & Activity'!$I$11:$I$33,"*I1*",'3. HR & Activity'!$K$11:$K$33) | G67: Reg reporting — HQ risk/finance pools
B68: I2 | C68: Credit Director | D68: =SUMIF('3. HR & Activity'!$I$11:$I$33,"*I2*",'3. HR & Activity'!$H$11:$H$33) | E68: =SUMIF('3. HR & Activity'!$I$11:$I$33,"*I2*",'3. HR & Activity'!$J$11:$J$33) | F68: =SUMIF('3. HR & Activity'!$I$11:$I$33,"*I2*",'3. HR & Activity'!$K$11:$K$33) | G68: Bureau reciprocity feeds — credit systems driver
B69: I3 | C69: Head of Digital | D69: =SUMIF('3. HR & Activity'!$I$11:$I$33,"*I3*",'3. HR & Activity'!$H$11:$H$33) | E69: =SUMIF('3. HR & Activity'!$I$11:$I$33,"*I3*",'3. HR & Activity'!$J$11:$J$33) | F69: =SUMIF('3. HR & Activity'!$I$11:$I$33,"*I3*",'3. HR & Activity'!$K$11:$K$33) | G69: Open Banking service — HQ tech pool
B70: CHECK — activity costs fully allocated to flows | D70: =SUMPRODUCT(('3. HR & Activity'!$I$11:$I$33<>"")*'3. HR & Activity'!$H$11:$H$33)-('4. Running Costs'!$C$25) | G70: tagged activity cost minus analyst & service payroll → 0 when every activity row carries a flow tag
B72: A zero in 'Activity cost' does NOT mean a free flow — see 'Costed via': those flows are costed through per-account drivers, HQ pools, or P&L lines. Bands are the default ±(act_lo/act_hi) factors pending evidenced per-activity ranges (IVE TPM discipline).
B74: BANK-BOUNDARY FIDELITY CHECK — every P&L money outflow ties to a flow (the money-outflow rule)
B75: P&L outflow | C75: Carried by flow | D75: Status
B76: Deposit interest paid | C76: SV-PP2 | D76: ✓
B77: Wholesale funding cost (incl. interest to BoE/markets) | C77: PartP1 — Bank of England | D77: ✓
B78: Staff salaries & benefits (front line + HQ) | C78: PartP3 — Employees | D78: ✓ (added)
B79: Premises · depreciation · other · tech & vendor payments | C79: PartP4 — Suppliers & vendors | D79: ✓ (added)
B80: Fraud & APP reimbursement to customers | C80: S4 outflow (fraud resolution) | D80: ✓
B81: FSCS levy | C81: PartP1 — FSCS | D81: ✓
B82: Tax (corporation tax + surcharge) | C82: PartP1 — HMRC | D82: ✓
B83: Dividends / required return on equity | C83: PartP2 — Shareholders | D83: ✓ (added)
B84: Expected credit losses | C84: non-cash provision; cash leaves at drawdown (LN-PP1), partial return via recoveries (in LN-WP workout) | D84: note
B86: MODULE ↔ FIN-SIM BRIDGE — live roll-up of each product module's economics (pulls from tabs 2 & 6)
B87: Module | C87: Product | D87: Fin-sim keys (tabs 2–6) | E87: Revenue (£/yr) | F87: Contribution (£/yr) | G87: Economic contribution (£/yr)
B88: CA | C88: Current account | D88: bca | E88: ='2. Revenues'!$M$5 | F88: ='6. Unit Economics'!C24 | G88: ='6. Unit Economics'!C25
B89: SV | C89: Savings & deposits | D89: sav + dep | E89: ='2. Revenues'!$M$6+'2. Revenues'!$M$7 | F89: ='6. Unit Economics'!D24+'6. Unit Economics'!E24 | G89: ='6. Unit Economics'!D25+'6. Unit Economics'!E25
B90: LN | C90: Lending & credit | D90: od + loan + af + inv | E90: ='2. Revenues'!$M$8+'2. Revenues'!$M$9+'2. Revenues'!$M$10+'2. Revenues'!$M$11 | F90: ='6. Unit Economics'!F24+'6. Unit Economics'!G24+'6. Unit Economics'!H24+'6. Unit Economics'!I24 | G90: ='6. Unit Economics'!F25+'6. Unit Economics'!G25+'6. Unit Economics'!H25+'6. Unit Economics'!I25
B91: CC | C91: Business credit card | D91: card | E91: ='2. Revenues'!$M$12 | F91: ='6. Unit Economics'!J24 | G91: ='6. Unit Economics'!J25
B92: PX | C92: Payments & FX | D92: fx | E92: ='2. Revenues'!$M$13 | F92: ='6. Unit Economics'!K24 | G92: ='6. Unit Economics'!K25
B93: TOTAL | E93: =SUM(E88:E92) | F93: =SUM(F88:F92) | G93: =SUM(G88:G92)
B94: The traceability chain: CTM state change → module WP (this tab) → activities tagged with the flow ID (tab 3, 'Flow' column) → FTEs & costs (tabs 3–4) → per-product economics (tab 6) → module roll-up above. One ID system end to end.
B96: BIAN COMPLETENESS CHECKLIST — cross-cutting capabilities that move the flows
B97: Capability | C97: BIAN business area | D97: 4-D classification | E97: Captured where | F97: Status
B98: Party reference data | C98: Reference Data | D98: Back-office activity | E98: HQ capability + CA-WP | F98: Captured
B99: Product directory & pricing | C99: Reference Data | D99: Back-office activity | E99: HQ capability | F99: Captured
B100: Customer access entitlement / authentication | C100: Sales & Service | D100: Enabling product | E100: E4 | F100: Captured (new)
B101: Financial message gateway (Open Banking / API) | C101: Operations & Execution | D101: Enabling product | E101: E3 | F101: Captured (new)
B102: Reconciliation | C102: Operations & Execution | D102: Money-flow capability | E102: *-PP flows + HQ | F102: Captured
B103: Position keeping (nostro / vostro) | C103: Operations & Execution | D103: Money-flow capability | E103: SV/LN PP flows + HQ | F103: Captured
B104: Regulatory compliance & reporting | C104: Risk & Compliance | D104: Back-office activity | E104: HQ + FSCS rail | F104: Captured
B105: Sanctions screening / CDD | C105: Risk & Compliance | D105: Back-office activity | E105: HQ (within fraud/AML) | F105: Captured
B106: Collections & recovery | C106: Operations & Execution | D106: Back-office activity | E106: HQ + LN-WP | F106: Captured
B107: Collateral administration | C107: Operations & Execution | D107: Back-office activity | E107: HQ + LN-WP | F107: Captured
B108: Fraud resolution | C108: Operations & Execution | D108: Support product | E108: S4 | F108: Captured
... B114: Finance / general ledger | C114: Business Support | D114: Money-flow capability | E114: HQ capability | F114: Captured
B116: Out of scope by design (BIAN domains not built): wholesale markets · trading · wealth / investment management · trade finance · corporate finance / capital markets · retail-only consumer products. Treasury kept minimal — liquidity / ALM + correspondent banking only.
B119: Source: BIAN Service Landscape v9.1 (bian.org). Confirm any service-domain name against the v9.1 matrix before external use — BIAN renames domains between versions.

Sheet 10. Elasticities
B1: ELASTICITIES — WHAT DRIVES PERFORMANCE, AND BY HOW MUCH
B2: Each input was bumped by +1% and the whole workbook recalculated. The figures below are the resulting % change in each output. An elasticity of +1.25 means a 1% rise in that input raises profit before tax by 1.25%. These are the workbook's own formulas, recalculated — not a separate estimate.
B3: STATIC BY DESIGN: computed against the central scenario at build time. Change an input materially and they move. Recompute with elasticity.py. Elasticities are local — they describe the slope at this operating point, not the whole surface, and they say nothing about what is actually movable.
B5: Computed at: PBT £4,552,743 · cost:income 45.7% · RoE 21.8%
B7: Input | C7: Value | D7: Unit | E7: e(PBT) | F7: e(Cost:income) | G7: e(RoE) | H7: e(Income)
B8: Term loans — customer rate | C8: 0.0625 | D8: % p.a. | E8: 1.247681 | F8: -0.59205795 | G8: 1.1483698 | H8: 0.59558415
B9: Reachable SMEs in region (R) | C9: 18750 | D9: businesses | E9: 1 | F9: 0 | G9: 0 | H9: 1
B10: Steady-state penetration (P) | C10: 0.16 | D10: % of reachable | E10: 1 | F10: 0 | G10: 0 | H10: 1
B11: Business current account — penetration | C11: 1 | D11: % of customers | E11: 0.53165022 | F11: -0.2263725 | G11: 0.4858716 | H11: 0.27635105
B12: Term loans — average balance | C12: 250000 | D12: £/loan | E12: 0.44852194 | F12: -0.25084081 | G12: -0.17262725 | H12: 0.25147161
B13: BCA — average credit balance | C13: 18000 | D13: £/account | E13: 0.42692862 | F13: -0.20096248 | G13: 0.392863 | H13: 0.20583388
B14: Term loans / commercial mortgages — penetration | C14: 0.12 | D14: % | E14: 0.41680875 | F14: -0.21781588 | G14: -0.20414433 | H14: 0.25147161
B15: Asset finance — customer yield | C15: 0.085 | D15: % p.a. | E15: 0.36199386 | F15: -0.17250074 | G15: 0.3334125 | H15: 0.17279881
B16: Invoice finance — average funds in use (advances) | C16: 150000 | D16: £/client | E16: 0.31018718 | F16: -0.15430746 | G16: 0.2098296 | H16: 0.15454593
B17: Notice & fixed deposits — rate paid | C17: 0.041 | D17: % p.a. | E17: -0.30692954 | F17: 0.14672868 | G17: -0.28284465 | H17: -0.1465137
B18: Invoice finance — penetration | C18: 0.03 | D18: % | E18: 0.29687548 | F18: -0.14043172 | G18: 0.19653121 | H18: 0.15454593
B19: Head office: technology & central operations | C19: 450 | D19: £/customer/yr | E19: -0.29652454 | F19: 0.30956618 | G19: -0.29652454 | H19: 0
... B91: Tax rate (corporation tax + bank surcharge) | C91: 0.28 | D91: % | E91: 0 | F91: 0 | G91: -0.38888889 | H91: 0

Sheet 11. Backtest
B1: BACKTEST — ALLICA BANK LIMITED, FY2023
B2: Nothing else in this workbook has been checked against a real outcome. This tab is that check. Allica is the closest listed-accounts analogue to the archetype modelled here: a UK bank serving established SMEs with commercial mortgages, asset finance, deposits and a business current account. FY2023 is used because its annual report publishes total operating income AND total operating expenses separately, which a cost test requires; the FY2024 release gives gross revenue and profit before tax but not the split. OakNorth is excluded for the same reason — no source found publishes its operating income and expenses separately.
B3: Method: the model was configured to Allica's observable shape — one operating unit, ~3,000 customers, £1.98bn of lending at a 7.5% yield, £2.5bn of term deposits, 2023 average Bank Rate 4.7%, no cards, no FX, no invoice finance, relationship-led throughout. Harness: backtest_allica.py.
C5: MODEL | D5: ACTUAL (audited) | E5: ratio | F5: Reading
B6: Total operating income | C6: 93514473 | D6: 86808000 | E6: 1.0772564 | F6: The revenue engine holds. 8% error on a real bank, from public inputs only — margins, transfer pricing and product economics reproduce.
B7: Total operating costs | C7: 8164139 | D7: 56438000 | E7: 0.14465677 | F7: The cost engine fails, and by an order of magnitude. This is the finding.
B8: Profit before tax | C8: 76640314 | D8: 16091000 | E8: 4.7629305 | F8: Follows the cost failure, not an independent error.
B9: Operating-unit FTE | C9: 45 | D9: 496 | E9: 0.090725806 | F9: Allica's 496 includes 200+ product and engineering staff building the platform; the model books those to head office, and books head office per customer.
B10: Cost:income ratio | C10: 0.0873 | D10: 0.65 | E10: 0.13430769 | F10: Allica's own disclosed ratio. The model's 8.7% is not a plausible bank.
B12: WHAT THE FAILURE MEANS
B13: • Head-office cost was modelled purely per customer. That is a scale assumption wearing the costume of a cost driver: it is only true near the book size the model was calibrated on. At Allica's customer count the model allocates £2.8m of head office where the real fixed platform, compliance and brand base is an order of magnitude larger.
B14: • A steady-state model cannot represent a bank that grew lending 47% and headcount from 324 to 496 in the year measured. Growth cost is excluded by construction, not by oversight.
B15: • The consequence for simulating new business ideas is direct: every new venture starts sub-scale, so a model that is only valid at scale cannot price one. This is the empirical version of the same limit as the missing time axis.
B16: • The fix this motivated is live: Inputs section N adds a fixed component to each head-office pool, defaulting to zero so v1.5 behaviour is unchanged. Setting it lets the model represent a bank away from at-scale.
B17: • What survives the test is worth as much as what fails. The revenue engine reproduced a real bank's operating income to within 8% from public inputs. That side of the model can now be relied on in a way it could not before this tab existed.
B19: OUT-OF-SAMPLE — CALIBRATE ON 2022-23, PREDICT 2024
B20: Fitting a model to the data it was calibrated on proves nothing. The cost structure below was calibrated on two published years and then used to predict a third it never saw. Harness: backtest_allica_oos.py.
B21: Year | C21: Lending book | D21: Operating cost | E21: Cost / book | F21: Elasticity vs prior year
B22: 2022 | C22: 1348166000 | D22: 41426000 | E22: 0.03072767 | F22: —
B23: 2023 | C23: 1976826000 | D23: 56438000 | E23: 0.028549807 | F23: 0.808
B24: 2024 | C24: 3000000000 | D24: 73148000 | E24: 0.024382667 | F24: 0.622
B25: 2024 operating cost is implied — income less impairment less the published profit before tax.
B26: Predicted 2024 profit before tax | C26: 23993000 | F26: cost carried forward at the 0.808 elasticity measured on 2022-23
B27: Actual 2024 profit before tax | C27: 29900000 | F27: published
B28: Error | C28: -0.198 | F28: under-predicts, because leverage steepened to 0.622 — efficiency improved faster than the prior year could have told you
B29: A structural model calibrated on two years of accounts predicted the third to within 20% on profit — the residual of three larger numbers, and the hardest line to get right. Three data points and one bank: directional evidence about structure, not a validated forecast.
B31: Source: Allica Bank Limited, Annual Report and Accounts 2023 (company number 07706156). Total operating income £86,808k; total operating expenses £56,438k; cost:income 65.0%; impairment charges £14,279k; profit before tax £16,091k; net interest margin 5.00%; loans and advances to customers £1,976,826k; colleagues at year end 496.
